[
  {
    "url": "https://neplays.com/article/151784",
    "title": "आर्मीलाई हराउँदै एपीएफ शीर्ष स्थानमा, सविन गुरुङ बने नायक",
    "pub_date": "2026-03-12 21:59:08",
    "fetched_at": "2026-03-12T16:17:05.860762+00:00",
    "portal": "Neplays",
    "profiles_matched": [],
    "keywords_matched": [],
    "snippet": "आर्मीलाई हराउँदै एपीएफ शीर्ष स्थानमा, सविन गुरुङ बने नायक\n- नेप्लेज\n- |\n- २०८२-११-२८\n- |\n- 22 पटक हेरिएको\nकाठमाडौं। राष्ट्रिय लिगअन्तर्गत विभागीय डर्बीमा एपीएफ फुटबल क्लबले त्रिभुवन आर्मी क्लबलाई पराजित गर्दै शीर्ष स्थानमा उक्लिएको छ।\nत्रिपुरेश्वरस्थित दशरथ रंगशालामा बिहीबार सम्पन्न दिनको तेस्रो तथा अन्तिम खेलमा एपीएफले आर्मीलाई १–० गोलले हराएको हो।\nखेलको ७६औँ मिनेटमा सविन गुरुङले गरेको गोल नै एपीएफका लागि निर्णायक बन्यो। त्यसपछि दुवै टोलीले थप गोल गर्ने प्रयास गरे पनि सफल हुन सकेनन्।\nयस जितसँगै",
    "content": "आर्मीलाई हराउँदै एपीएफ शीर्ष स्थानमा, सविन गुरुङ बने नायक\n- नेप्लेज\n- |\n- २०८२-११-२८\n- |\n- 22 पटक हेरिएको\nकाठमाडौं। राष्ट्रिय लिगअन्तर्गत विभागीय डर्बीमा एपीएफ फुटबल क्लबले त्रिभुवन आर्मी क्लबलाई पराजित गर्दै शीर्ष स्थानमा उक्लिएको छ।\nत्रिपुरेश्वरस्थित दशरथ रंगशालामा बिहीबार सम्पन्न दिनको तेस्रो तथा अन्तिम खेलमा एपीएफले आर्मीलाई १–० गोलले हराएको हो।\nखेलको ७६औँ मिनेटमा सविन गुरुङले गरेको गोल नै एपीएफका लागि निर्णायक बन्यो। त्यसपछि दुवै टोलीले थप गोल गर्ने प्रयास गरे पनि सफल हुन सकेनन्।\nयस जितसँगै एपीएफले १० खेलबाट २४ अंक जोड्दै तालिकाको शीर्ष स्थान कब्जा गरेको छ। समान खेल खेलेको आर्मी भने २० अंकसहित चौथो स्थानमा रहेको छ।",
    "images": [
      "https://neplays.com/img/new-logo.png",
      "https://neplays.com/img/posts/IMG_20260312_185440.jpg",
      "https://neplays.com/img/posts/FB_IMG_1773315311259.jpg",
      "https://neplays.com/img/posts/received_1630983168037193.jpeg",
      "https://neplays.com/img/posts/Sakata Fc.jpg",
      "https://neplays.com/img/posts/NRT.JPG",
      "https://neplays.com/img/posts/Church 2082.jpg",
      "https://neplays.com/img/posts/Dem.jpg",
      "https://neplays.com/img/posts/FB_IMG_1773281708286.jpg",
      "https://neplays.com/img/ads-img/ads-63401c290b7deads-61d4579d552abKelmi1.gif"
    ]
  },
  {
    "url": "https://www.pardafas.com/2026/03/12/162787/",
    "title": "सूर्यविनायकद्वारा प्रहरी बृत्त जगातीलाई गाडी हस्तान्तरण",
    "pub_date": "2026-03-12 21:58:04",
    "fetched_at": "2026-03-12T16:17:09.849665+00:00",
    "portal": "Pardafas",
    "profiles_matched": [],
    "keywords_matched": [],
    "snippet": "सूर्यविनायकद्वारा प्रहरी बृत्त जगातीलाई गाडी हस्तान्तरण\nसूर्यविनायक नगरपालिकाले प्रहरी बृत्त जगातीलाई गाडी हस्तान्तरण गरेको छ ।\nनगरपालिकामा आज आयोजित कार्यक्रममा नगर प्रमुख वासुदेव थापाले जिल्ला प्रहरी परिसर भक्तपुरका प्रमुख एवं प्रहरी उपरीक्षक सूर्यबहादुर खड्कालाई गाडीको साँचो, ब्लूबुक तथा कागजपत्र हस्तान्तरण गरेका हुन् ।\nसो अवसरमा नगर प्रमुख थापाले जेनजी आन्दोलनमा क्रममा प्रहरी बृत्त जगातीको भवन पूर्ण रुपमा क्षति भएको अवस्थामा भवन पुनःनिर्माणका लागि नगरपालिकाले रु १५ लाख सहयोग गरेको जानकारी दि",
    "content": "सूर्यविनायकद्वारा प्रहरी बृत्त जगातीलाई गाडी हस्तान्तरण\nसूर्यविनायक नगरपालिकाले प्रहरी बृत्त जगातीलाई गाडी हस्तान्तरण गरेको छ ।\nनगरपालिकामा आज आयोजित कार्यक्रममा नगर प्रमुख वासुदेव थापाले जिल्ला प्रहरी परिसर भक्तपुरका प्रमुख एवं प्रहरी उपरीक्षक सूर्यबहादुर खड्कालाई गाडीको साँचो, ब्लूबुक तथा कागजपत्र हस्तान्तरण गरेका हुन् ।\nसो अवसरमा नगर प्रमुख थापाले जेनजी आन्दोलनमा क्रममा प्रहरी बृत्त जगातीको भवन पूर्ण रुपमा क्षति भएको अवस्थामा भवन पुनःनिर्माणका लागि नगरपालिकाले रु १५ लाख सहयोग गरेको जानकारी दिए । उनले भने, “प्रहरीको भवनसँगै सबै गाडी जलेर ध्वस्त भएकाले गस्ती गर्न सहज होस भनेर रु ४३ लाखमा गाडी किनेर सहयोग गरेका हौँ ।”\nकार्यक्रममा प्रमुख जिल्ला अधिकारी उमेशकुमार ढकाल, नगरपालिकाका प्रमुख प्रशासकीय अधिकृत युवराज आचार्य, सूर्यविनायक नगरपालिका वडाध्यक्षहरु सानुकाजी कायस्थ, प्रदीप कार्की, लक्षुराम न्यौपाने, रविन्द्र सापकोटा, पुष्पराज बस्नेत र शिवराम राउत, कार्यपालिका सदस्य तारा सापकोटा, शर्मिला थापालगायतले आ–आफ्नो धारणा राखेका थिए ।\nप्रतिक्रिया",
    "images": [
      "https://www.pardafas.com/wp-content/uploads/2022/06/pardafas-logo.png",
      "https://www.pardafas.com/wp-content/uploads/2025/12/Comp-02.gif",
      "https://www.pardafas.com/wp-content/uploads/2022/06/pardafas-logo.png",
      "https://www.pardafas.com/wp-content/uploads/2026/03/police-suryabinayak-gadi-hastantaran-450x250.jpg",
      "https://www.pardafas.com/wp-content/uploads/2026/01/lp-gyash-450x250.jpg",
      "https://www.pardafas.com/wp-content/uploads/2026/03/naka-450x250.jpg",
      "https://www.pardafas.com/wp-content/uploads/2026/03/bike-450x250.jpg",
      "https://www.pardafas.com/wp-content/uploads/2026/02/election-2082--450x250.jpeg",
      "https://www.pardafas.com/wp-content/uploads/2022/07/Election-Comission-Nepal-450x250.jpg",
      "https://www.pardafas.com/wp-content/uploads/2022/06/pardafas-logo.png"
    ]
  },
  {
    "url": "https://gorkhapatraonline.com/news/196170",
    "title": "आयोगद्वारा निर्वाचन खर्च सार्वजनिक गर्न अनुरोध",
    "pub_date": "2026-03-12 21:56:08",
    "fetched_at": "2026-03-12T16:17:14.500708+00:00",
    "portal": "Gorkhapatraonline",
    "profiles_matched": [
      "Election Monitoring"
    ],
    "keywords_matched": [
      "निर्वाचन",
      "निर्वाचन आयोग"
    ],
    "snippet": "काठमाडौँ, फागुन २८ गते । निर्वाचन आयोगले उम्मेदवारलाई आफ्नो निर्वाचन खर्च विवरण बुझाउन अनुरोध गरेको छ ।\nआयोगले आज विज्ञप्ति जारी गरी निर्वाचन सम्पन्न भएको मितिले ३५ दिनभित्र राजनीतिक दलले निर्वाचन आयोगमा र उम्मेदवारले आफ्नो जिल्लामा रहेको प्रदेश-जिल्ला निर्वाचन कार्यालयमा निर्वाचन प्रचारप्रसारमा भएको आम्दानी तथा खर्चको विवरण तथा सो विवरण सार्वजनिक गरेको जानकारी गराउन अनुरोध गरेको हो ।\nआफ्नो जिल्लामा रहेको प्रदेश-जिल्ला निर्वाचन कार्यालयको सूचना पाटी, सम्बन्धित गाउँपालिका वा नगरपालिका वा वडा कार्",
    "content": "काठमाडौँ, फागुन २८ गते । निर्वाचन आयोगले उम्मेदवारलाई आफ्नो निर्वाचन खर्च विवरण बुझाउन अनुरोध गरेको छ ।\nआयोगले आज विज्ञप्ति जारी गरी निर्वाचन सम्पन्न भएको मितिले ३५ दिनभित्र राजनीतिक दलले निर्वाचन आयोगमा र उम्मेदवारले आफ्नो जिल्लामा रहेको प्रदेश-जिल्ला निर्वाचन कार्यालयमा निर्वाचन प्रचारप्रसारमा भएको आम्दानी तथा खर्चको विवरण तथा सो विवरण सार्वजनिक गरेको जानकारी गराउन अनुरोध गरेको हो ।\nआफ्नो जिल्लामा रहेको प्रदेश-जिल्ला निर्वाचन कार्यालयको सूचना पाटी, सम्बन्धित गाउँपालिका वा नगरपालिका वा वडा कार्यालयको सूचना पाटी, राजनीतिक दलको जुनसुकै तहको कार्यालय वा वेवसाइट (राजनीतिक दलको तर्फबाट उम्मेदवार भएका उम्मेदवारको हकमा), आमसञ्चार माध्यम (पत्रपत्रिका, रेडियो, टेलिभिजन आदि) वा सामाजिक सञ्जाल (फेसबुक, ट्विटर, ईन्स्टाग्राम आदि) मा आफ्नो निर्वाचन विवरण सार्वजनिक गर्न आयोगको अनुरोध छ ।\nनिर्वाचन खर्चको विवरण नबुझाउने तथा सार्वजनिक नगर्ने एवं निर्वाचन खर्चको विवरण सार्वजनिक गरी त्यसरी सार्वजनिक गरेको विवरणको प्रमाणसहित लिखित जानकारी आयोग तथा सम्बन्धित निर्वाचन कार्यालयमा नदिने राजनीतिक दल तथा उम्मेदवारको हकमा निर्वाचन (कसुर तथा सजाय) ऐन, २०७३ को दफा ३१ बमोजिम कारबाही हुने आयोगले जनाएको छ ।\nनिर्वाचन ऐन, २०७४ को दफा ७२ को उपदफा (४) बमोजिम निर्वाचन प्रचार प्रसारमा गरेको खर्चको विवरण पहिलो हुने निर्वाचित हुने प्रणालीतर्फ उम्मेदवारले सम्बन्धित जिल्ला निर्वाचन कार्यालयमा र समानुपातिक निर्वाचन प्रणालीतर्फको हकमा सम्बन्धित राजनीतिक दलले निर्वाचन आयोगसमक्ष तोकिएको ढाँचामा निर्वाचन प्रचारप्रसारमा भएको आम्दानी र खर्चको विवरण सार्वजनिक गर्नु भनिएको छ ।\nनिर्वाचन (कसुर तथा सजाय) ऐन, २०७३ को दफा ३१ को उपदफा (२) बमोजिम खर्चको विवरण सम्बन्धित सबैको जानकारीको लागि आयोगले तोके बमोजिम सार्वजनिक गर्नुपर्नेछ भन्ने कानुनी व्यवस्था छ । रासस",
    "images": [
      "https://gorkhapatraonline.com/storage/media/311657/gp-logo-black.svg",
      "https://gorkhapatraonline.com/storage/media/311657/gp-logo-black.svg",
      "https://gorkhapatraonline.com/commons/header-icons/trn.png",
      "https://gorkhapatraonline.com/commons/header-icons/muna.png",
      "https://gorkhapatraonline.com/commons/header-icons/madhupark.png",
      "https://gorkhapatraonline.com/commons/header-icons/yuba-manch.png",
      "https://gorkhapatraonline.com/commons/header-icons/naya-nepal.png",
      "https://gorkhapatraonline.com/storage/media/343090/election.jpg",
      "https://gorkhapatraonline.com/storage/media/146779/conversions/gopa-thumb.jpg",
      "https://gorkhapatraonline.com/storage/media/146779/conversions/gopa-thumb.jpg"
    ]
  },
  {
    "url": "https://nepalkhabar.com/economy/268337-2026-3-12-21-52-58",
    "title": "रुद्रवेणी–वामीटक्सार–खर्बाङ सडक एक महिना बन्द हुने",
    "pub_date": "2026-03-12 21:52:58",
    "fetched_at": "2026-03-12T16:17:18.167990+00:00",
    "portal": "Nepalkhabar",
    "profiles_matched": [],
    "keywords_matched": [],
    "snippet": "राष्ट्रिय राजमार्गअन्तर्गत गुल्मीको रुद्रवेणी–वामीटक्सार–खर्बाङ सडक एक महिनाका लागि पूर्णरुपमा बन्द हुनेभएको छ।\nउक्त सडकखण्डअन्तर्गत सत्यवती गाउँपालिकास्थित सिस्ने भीरमा सडक स्तरोन्नति गर्ने कार्य सुरु हुने भएको हुँदा कारण आगामी चैत १ देखि चैत ३० गतेसम्म सडक बन्द गर्ने निर्णय गरिएको हो।\nसडक डिभिजन कार्यालय पाल्पाको २०८२ फागुन २८ गतेको पत्रअनुसार उक्त राजमार्गको अति संवेदनशील र साँघुरो स्थान सिस्ने भीरमा सडक कटिङ गर्ने क्रममा ढुङ्गा खस्ने जोखिम बढेकाले दुर्घटना हुनसक्ने सम्भावनालाई ध्यानमा राख्दै",
    "content": "राष्ट्रिय राजमार्गअन्तर्गत गुल्मीको रुद्रवेणी–वामीटक्सार–खर्बाङ सडक एक महिनाका लागि पूर्णरुपमा बन्द हुनेभएको छ।\nउक्त सडकखण्डअन्तर्गत सत्यवती गाउँपालिकास्थित सिस्ने भीरमा सडक स्तरोन्नति गर्ने कार्य सुरु हुने भएको हुँदा कारण आगामी चैत १ देखि चैत ३० गतेसम्म सडक बन्द गर्ने निर्णय गरिएको हो।\nसडक डिभिजन कार्यालय पाल्पाको २०८२ फागुन २८ गतेको पत्रअनुसार उक्त राजमार्गको अति संवेदनशील र साँघुरो स्थान सिस्ने भीरमा सडक कटिङ गर्ने क्रममा ढुङ्गा खस्ने जोखिम बढेकाले दुर्घटना हुनसक्ने सम्भावनालाई ध्यानमा राख्दै सडक बन्द गर्ने निर्णय गरिएको सहायक प्रमुख जिल्ला अधिकारी हरिप्रसाद गैरेले जानकारी दिए।\nप्रशासनले सो सडक स्तरोन्नतिको काम गर्दा सवारीसाधनलाई वैकल्पिक मार्ग प्रयोग गरी आवागमनका गर्न आग्रह गरेको छ। जिल्ला प्रशासन कार्यालयले वैकल्पिक सडकका रूपमा सोता–तल्लोरोड–रुपाकोट–दोकुवा–सालघारी–चोरकाटे तथा मजुवा–दम्का–रुपाकोट–म्यालपोखरी–चोरकाटे सडक प्रयोग गर्न आग्रह गरेको छ।\nसडक स्तरोन्नतिको काम सम्पन्न गर्न सहयोगका लागि सरोकारवालालाई अनुरोध गरेको छ। प्रशासनले आज सार्वजनिक रुपमा सूचना जारी गरी उक्त सडक एक महिना २४सै घण्टा बन्द रहने जनाएको हो। सडक डिभिजन कार्यालय पाल्पाले गत माघ २६ देखि फागुन १५ गतेसम्म आंशिक रुपमा सडक बन्द गरी स्तरोन्नतिको काम गरेको थियो। रासस\nप्रतिक्रिया",
    "images": [
      "https://certify.alexametrics.com/atrk.gif?account=xp3Mn1QolK10uG",
      "https://nepalkhabar.prixacdn.net/media/albums/logo-np-inverse_KvRlHqXMS9.png",
      "https://nepalkhabar.prixacdn.net/static/normal/images/assets/unicode1.svg",
      "https://nepalkhabar.prixacdn.net/media/albums/logo-np-inverse_KvRlHqXMS9.png",
      "https://nepalkhabar.prixacdn.net/media/albums/logo-np-inverse_KvRlHqXMS9.png",
      "https://nepalkhabar.prixacdn.net/static/normal/images/assets/unicode1.svg",
      "https://nepalkhabar.prixacdn.net/static/normal/images/assets/unicode1.svg",
      "https://nepalkhabar.prixacdn.net/media/advertisements/825X100px_10_jhrMoWTdUQ.jpg",
      "https://nepalkhabar.prixacdn.net/media/advertisements/800X200px_9_GfHu0GxeAZ.jpg",
      "https://nepalkhabar.prixacdn.net/media/albums/Sadak-Dhunga_63HD6CJCxd.png"
    ]
  },
  {
    "url": "https://farakdhar.com/story/163438",
    "title": "कम्बोडियामा अलपत्र १६ नेपालीको उद्धार, स्वदेश फिर्ता",
    "pub_date": "2026-03-12 21:51:46",
    "fetched_at": "2026-03-12T16:17:22.581588+00:00",
    "portal": "Farakdhar",
    "profiles_matched": [],
    "keywords_matched": [],
    "snippet": "मानव तस्करको प्रलोभनमा परी विभिन्न माध्यमबाट कम्बोडिया पुगेका १६ जना नेपाली नागरिकको उद्धार गरी स्वदेश फर्काइएको छ ।\nकम्बोडियामा अवैध रूपमा सञ्चालित अनलाइन स्क्यामिङ केन्द्र र क्यासिनोमा अनलाइन ठगी लगायतका गैरकानुनी काममा लगाइएका तथा बिनाभिसा बसिरहेका उनीहरूलाई नेपाली राजदूतावास, बैंककको पहल र कम्बोडिया सरकारको सहयोगमा उद्धार गरिएको हो । यस प्रक्रियामा गैरआवासीय नेपाली संघ कम्बोडियाले सहजीकरण गरेको छ ।\nयसैगरी, अलपत्र परेका वा कठिन परिस्थितिमा रहेका अन्य नेपालीहरूलाई समेत नेपाल फर्काउने पहल भइरहे",
    "content": "मानव तस्करको प्रलोभनमा परी विभिन्न माध्यमबाट कम्बोडिया पुगेका १६ जना नेपाली नागरिकको उद्धार गरी स्वदेश फर्काइएको छ ।\nकम्बोडियामा अवैध रूपमा सञ्चालित अनलाइन स्क्यामिङ केन्द्र र क्यासिनोमा अनलाइन ठगी लगायतका गैरकानुनी काममा लगाइएका तथा बिनाभिसा बसिरहेका उनीहरूलाई नेपाली राजदूतावास, बैंककको पहल र कम्बोडिया सरकारको सहयोगमा उद्धार गरिएको हो । यस प्रक्रियामा गैरआवासीय नेपाली संघ कम्बोडियाले सहजीकरण गरेको छ ।\nयसैगरी, अलपत्र परेका वा कठिन परिस्थितिमा रहेका अन्य नेपालीहरूलाई समेत नेपाल फर्काउने पहल भइरहेको छ ।\nकम्बोडियामा नेपाली नागरिकहरू अनलाइन ठगी लगायतका गैरकानुनी काममा लगाइएको र बिनाभिसा वा भिसा अवधिभन्दा बढी समय बसिरहेको जानकारी राजदूतावासलाई प्राप्त भएको भन्दै यस्तो अवस्थामा रहनुभएका नेपाली नागरिकहरूलाई नेपाल फर्कन सहज बनाउनका लागि नेपाली राजदूतावास, बैंकक वा गैरआवासीय नेपाली संघ, कम्बोडियाका निम्न प्रतिनिधिहरूलाई यथाशीघ्र सम्पर्क गर्न अनुरोध गरेको छ ।\nस्क्यामिङ केन्द्रहरूमा काम लगाइएका व्यक्तिको राहदानी कम्पनीले नै राख्ने गरेको वा केन्द्र स्थानान्तरण हुँदा राहदानी हराएको पाइएको छ। यस्तो अवस्थामा स्वदेश फर्किन चाहने नेपालीका लागि राजदूतावासले निःशुल्क एकतर्फी यात्रा अनुमतिपत्र निजहरूको ठेगानामा पठाइदिने व्यवस्था गरेको छ।\nफरकधारमा प्रकाशित कुनै समाचारमा तपाईंको गुनासो भए हामीलाई [email protected] मा इमेल गर्न सक्नुहुनेछ । यही इमेलमा तपाईंले आफ्नो विचार वा विश्लेषण, सल्लाह र सुझाव पनि पठाउन सक्नुहुनेछ । हामीसँग तपाईं फेसबुक, ट्विटर, इन्स्टाग्राम, युट्युबमा पनि जोडिन सक्नुहुन्छ ।",
    "images": [
      "https://certify.alexametrics.com/atrk.gif?account=K32Gs1DTcA20Ug",
      "https://fdcdn.prixacdn.net/media/albums/logo_fd_icByRp1WFp.png",
      "https://fdcdn.prixacdn.net/static/assets/images/farakdhar-logo4.png",
      "https://fdcdn.prixacdn.net/media/albums/logo_fd_icByRp1WFp.png",
      "https://fdcdn.prixacdn.net/media/albums/logo_fd_icByRp1WFp.png",
      "https://fdcdn.prixacdn.net/media/albums/logo_fd_icByRp1WFp.png",
      "https://fdcdn.prixacdn.net/media/albums/fd_pkaLV4MyIb.png",
      "https://fdcdn.prixacdn.net/media/albums/camnodia_QPDZIWdYGH.jpg",
      "https://fdcdn.prixacdn.net/media/EVEREST_COLLEGE_1_25tgU4qzW3.gif",
      "https://fdcdn.prixacdn.net/media/EDF_Admissions_Google_Ad.gif"
    ]
  },
  {
    "url": "https://www.ratopati.com/story/550159/us-trade-deficit-wider-than-expected-in-january",
    "title": "जनवरीमा अमेरिकी व्यापार घाटा अपेक्षा गरिएभन्दा बढी",
    "pub_date": "2026-03-12 21:50:08",
    "fetched_at": "2026-03-12T16:17:26.465618+00:00",
    "portal": "Ratopati",
    "profiles_matched": [],
    "keywords_matched": [],
    "snippet": "जनवरीमा अमेरिकी व्यापार घाटा अपेक्षा गरिएभन्दा बढी\nअमेरिका । जनवरीमा अमेरिकी व्यापार घाटा विश्लेषकहरूले अपेक्षा गरेभन्दा बढी खुम्चिएको अमेरिकी सरकारी तथ्याङ्कले बिहीबार देखाएको छ ।\nवाणिज्य मन्त्रालयका अनुसार जनवरीमा व्यापार घाटा डिसेम्बरको २५.३ प्रतिशतभन्दा बढेर ५४.५ अर्ब डलर पुगेको थियो । गत वर्ष पुनः ह्वाइट हाउस फर्केपछि राष्ट्रपति डोनाल्ड ट्रम्पको द्रुत परिवर्तनमा गरिएको करका कारण विश्वको सबैभन्दा ठूलो अर्थतन्त्र अमेरिकामा व्यापार प्रवाहमा असर परेको छ, यद्यपि गत महिना सर्वोच्च अदालतले ती मध्य",
    "content": "जनवरीमा अमेरिकी व्यापार घाटा अपेक्षा गरिएभन्दा बढी\nअमेरिका । जनवरीमा अमेरिकी व्यापार घाटा विश्लेषकहरूले अपेक्षा गरेभन्दा बढी खुम्चिएको अमेरिकी सरकारी तथ्याङ्कले बिहीबार देखाएको छ ।\nवाणिज्य मन्त्रालयका अनुसार जनवरीमा व्यापार घाटा डिसेम्बरको २५.३ प्रतिशतभन्दा बढेर ५४.५ अर्ब डलर पुगेको थियो । गत वर्ष पुनः ह्वाइट हाउस फर्केपछि राष्ट्रपति डोनाल्ड ट्रम्पको द्रुत परिवर्तनमा गरिएको करका कारण विश्वको सबैभन्दा ठूलो अर्थतन्त्र अमेरिकामा व्यापार प्रवाहमा असर परेको छ, यद्यपि गत महिना सर्वोच्च अदालतले ती मध्ये ठूलो हिस्सा खारेज गरेको थियो।\nतथ्याङ्कले कर प्रणालीलाई प्रतिबिम्बित गर्दछ जुन अब पुरानो भइसकेको छ । व्यापार अनिश्चितताले अझै पनि परिणामलाई छायाँमा पारेको छ ।\nअदालतको फैसलापछि राष्ट्रपति ट्रम्पले विभिन्न आयातमा १० प्रतिशत अस्थायी कर लगाउनुभएको थियो तर इयुले ट्रम्प सम्झौता अनुरूप चल्ने प्रतिवद्धता व्यक्त गर्नुभएको जनाएको थियो ।\nबुधबार अमेरिकी प्रशासनले आफ्नो पूरानै व्यापार एजेन्डालाई पुनरुत्थान गर्ने चाहनाका साथ दर्जनौँ व्यापारिक साझेदारहरूमा नयाँ अनुसन्धानको घोषणा गरेको छ ।\nऔद्योगिक आपूर्ति र कम्प्युटरदेखि नागरिक विमानसम्मको पुँजीगत सामानका कारण निर्यात ५.५ प्रतिशतले बढेर ३०२.१ अर्ब अमेरिकी डलर पुगेको छ । तर औषधि जस्ता उपभोग्य वस्तुको निर्यात पछि हटेको छ । यसैबीच, अमेरिकी आयात ०.७ प्रतिशतले घटेर ३५६.६ अर्ब डलर पुगेको छ ।\nखबर पढेर तपाईलाई कस्तो महसुस भयो ?\nप्रतिक्रिया\nभर्खरै\n-\nजनवरीमा अमेरिकी व्यापार घाटा अपेक्षा गरिएभन्दा बढी\n-\nराहदानी विभागले भन्यो– अन्तरिम अवधिमा सेवा प्रभावित हुन सक्छ\n-\nअमेरिकाले उल्लङ्घन गरेका व्यापार सम्झौताको ‘दृढताका साथ प्रतिक्रिया’ दिइनेः इयु\n-\nमुलुकको राजनीतिक परिवर्तनमा महिलाको योगदान महत्वपूर्ण : पूर्वराष्ट्रपति भण्डारी\n-\nसेतीमा दैनिक सेवा लिने बिरामीको सङ्ख्या बढ्दै\n-\n‘अस्पतालले दिने सेवामा सर्वसाधारणको सहज पहुँच आवश्यक’",
    "images": [
      "https://www.ratopati.com/build/img/gamepad.png",
      "https://www.ratopati.com/build/img/editor-new.png",
      "https://www.ratopati.com/build/img/keyboard.png",
      "https://www.ratopati.com/build/img/calendar.png",
      "https://npcdn.ratopati.com/media/setting/ratopati-logo_qQKWIp37FR.png",
      "https://www.ratopati.com/build/img/icon-search.png",
      "https://npcdn.ratopati.com/media/news/accident1_0HVVwEUEAJ.jpg",
      "https://npcdn.ratopati.com/media/news/28_LKbWztZouV.jpg",
      "https://npcdn.ratopati.com/media/news/mundum_2MUBe52naH.png",
      "https://rpcdn.ratopati.com/media/albums/matgadana_QLMADztZzv.jpg"
    ]
  },
  {
    "url": "https://www.pardafas.com/2026/03/12/162785/",
    "title": "अब प्रति सिलिण्डर आधा ग्यास ९५५",
    "pub_date": "2026-03-12 21:48:55",
    "fetched_at": "2026-03-12T16:17:30.917066+00:00",
    "portal": "Pardafas",
    "profiles_matched": [],
    "keywords_matched": [],
    "snippet": "अब प्रति सिलिण्डर आधा ग्यास ९५५\n२८ फागुन २०८२ २१:४८\nनेपाल आयल निगमले ग्यास सिलिण्डरमा ७.१ किलो एलपी ग्यास भरी प्रति सिलिण्डर आधा ९५५ मा बिक्री वितरण गर्ने निर्णय गरेको छ ।\nनिगमले आज विज्ञप्ति जारी गरी हालको परिस्थितिलाई दृष्टिगत गरी एलपी ग्यासको आपूर्ति तथा वितरण प्रणालीलाई व्यवस्थित बनाइ आम उपभोक्ताको माग बमोजिम ग्यास उपलब्ध हुने अवस्थाको सहजीकरणका लागि निगमले शुक्रबारदेखि लागू हुने गरी अर्को निर्णय नभएसम्म ग्यास सिलिण्डरमा ७.१ किलो एलपी ग्यास भरी प्रति सिलिण्डर आधा मूल्य रु ९५५ मा बिक्री वितरण",
    "content": "अब प्रति सिलिण्डर आधा ग्यास ९५५\n२८ फागुन २०८२ २१:४८\nनेपाल आयल निगमले ग्यास सिलिण्डरमा ७.१ किलो एलपी ग्यास भरी प्रति सिलिण्डर आधा ९५५ मा बिक्री वितरण गर्ने निर्णय गरेको छ ।\nनिगमले आज विज्ञप्ति जारी गरी हालको परिस्थितिलाई दृष्टिगत गरी एलपी ग्यासको आपूर्ति तथा वितरण प्रणालीलाई व्यवस्थित बनाइ आम उपभोक्ताको माग बमोजिम ग्यास उपलब्ध हुने अवस्थाको सहजीकरणका लागि निगमले शुक्रबारदेखि लागू हुने गरी अर्को निर्णय नभएसम्म ग्यास सिलिण्डरमा ७.१ किलो एलपी ग्यास भरी प्रति सिलिण्डर आधा मूल्य रु ९५५ मा बिक्री वितरण गर्ने निर्णय भएको जनाएको छ । आम उपभोक्ता वर्गले सोहीअनुसार एलपी ग्यास खरिद गर्न निगमले अनुरोध गरेको छ ।\nनिगमले निगमले नियमित रुपमा माग अनुरूप नै एलपी ग्यासको आयात तथा वितरण गरिरहेको भए पनि विगत दुई÷तीन महिनादेखि काठमाडौँ उपत्यकामा ग्यासको माग उच्च देखिएको र यसैबीच मध्यपूर्व क्षेत्रमा भइरहेको युद्धका कारण पेट्रोलियम पदार्थ तथा एलपी ग्यासको आपूर्तिमा विश्वव्यापी रूपमा असर परिरहेको प्रष्ट पारेको छ ।\nप्रतिक्रिया",
    "images": [
      "https://www.pardafas.com/wp-content/uploads/2022/06/pardafas-logo.png",
      "https://www.pardafas.com/wp-content/uploads/2025/12/Comp-02.gif",
      "https://www.pardafas.com/wp-content/uploads/2022/06/pardafas-logo.png",
      "https://www.pardafas.com/wp-content/uploads/2026/03/police-suryabinayak-gadi-hastantaran-450x250.jpg",
      "https://www.pardafas.com/wp-content/uploads/2026/01/lp-gyash-450x250.jpg",
      "https://www.pardafas.com/wp-content/uploads/2026/03/naka-450x250.jpg",
      "https://www.pardafas.com/wp-content/uploads/2026/03/bike-450x250.jpg",
      "https://www.pardafas.com/wp-content/uploads/2026/02/election-2082--450x250.jpeg",
      "https://www.pardafas.com/wp-content/uploads/2022/07/Election-Comission-Nepal-450x250.jpg",
      "https://www.pardafas.com/wp-content/uploads/2022/06/pardafas-logo.png"
    ]
  },
  {
    "url": "https://nepalnews.com/2026/03/12/number-of-patients-receiving-daily-services-in-seti-increasing/",
    "title": "सेतीमा दैनिक सेवा लिने बिरामीको सङ्ख्या बढ्दै",
    "pub_date": "2026-03-12 21:47:48",
    "fetched_at": "2026-03-12T16:17:35.644742+00:00",
    "portal": "Nepalnews",
    "profiles_matched": [],
    "keywords_matched": [],
    "snippet": "कैलाली। धनगढीस्थित सेती प्रादेशिक अस्पतालमा दैनिक सेवा लिने बिरामीको सङ्ख्या बढ्दै गएको छ । गर्मीयामको समय र यो साता प्रदूषण बढेकाले अस्पतालमा दैनिक सेवा लिने बिरामीको सङ्ख्या बढ्दै गएको हो ।\nअस्पतालका सूचना अधिकारी तथा मेडिकल रेकर्डर किशोरप्रसाद श्रेष्ठका अनुसार अस्पतालमा सेवा लिने बिरामीको सङ्ख्या दैनिक एक हजार ८०० सम्म पुगेको छ । प्रदूषणका बढेकाले अनावश्यक बाहिर ननिस्किन अस्पतालले अनुरोध गरेको छ । सूचना अधिकारी श्रेष्ठका अनुसार आकस्मिक कक्षमा बिरामीको सङ्ख्या दैनिक बढ्दै गएको छ ।\nअस्पतलाको ओप",
    "content": "कैलाली। धनगढीस्थित सेती प्रादेशिक अस्पतालमा दैनिक सेवा लिने बिरामीको सङ्ख्या बढ्दै गएको छ । गर्मीयामको समय र यो साता प्रदूषण बढेकाले अस्पतालमा दैनिक सेवा लिने बिरामीको सङ्ख्या बढ्दै गएको हो ।\nअस्पतालका सूचना अधिकारी तथा मेडिकल रेकर्डर किशोरप्रसाद श्रेष्ठका अनुसार अस्पतालमा सेवा लिने बिरामीको सङ्ख्या दैनिक एक हजार ८०० सम्म पुगेको छ । प्रदूषणका बढेकाले अनावश्यक बाहिर ननिस्किन अस्पतालले अनुरोध गरेको छ । सूचना अधिकारी श्रेष्ठका अनुसार आकस्मिक कक्षमा बिरामीको सङ्ख्या दैनिक बढ्दै गएको छ ।\nअस्पतलाको ओपिडी, डाइलासिस, बिमामा सेवा लिने बिरामीको सङ्ख्यामा वृद्धि भएको छ । सूचना अधिकारी श्रेष्ठले अझै बिरामीको सङ्ख्या बढ्न सक्ने बताए । यसका लागि आवश्यक व्यवस्थापन गर्न अस्पताल व्यवस्थापन लागि परेको उनले बताए । सीमित स्रोतसाधनको बावजुत अस्पतालले गुणस्तरिय सेवा प्रदान गर्दै आएको छ ।\nसेती प्रादेशिक अस्पतालमा कैलाली, कञ्चनपुरलगायत सुदूरका पहाडी जिल्लाबाट नागरिक उपचार गर्न आउने गरेका छन् ।",
    "images": [
      "https://english.nepalnews.com/wp-content/uploads/2025/01/Nepal-news-white.png",
      "https://english.nepalnews.com/wp-content/uploads/2025/01/Nepal-news-white.png",
      "https://english.nepalnews.com/wp-content/uploads/2025/01/close.png",
      "https://english.nepalnews.com/wp-content/uploads/2025/01/direct-flight.png",
      "https://english.nepalnews.com/wp-content/uploads/2025/01/cloudy-day.png",
      "https://english.nepalnews.com/wp-content/uploads/2025/01/air-quality.png",
      "https://english.nepalnews.com/wp-content/uploads/2025/01/change.png",
      "https://english.nepalnews.com/wp-content/uploads/2025/01/gold.png",
      "https://nepalnews.com/wp-content/uploads/2025/08/favicon-01.png",
      "https://nepalnews.com/wp-content/uploads/2026/03/seti.jpg"
    ]
  },
  {
    "url": "https://singhadurbarnews.com/2026/03/187469?npatro=1",
    "title": "नाडाको नवनिर्वाचित अध्यक्षलाई पदभार हस्तान्तरण तथा सपथ ग्रहण सम्पन्न",
    "pub_date": "2026-03-12 21:45:07",
    "fetched_at": "2026-03-12T16:17:41.002307+00:00",
    "portal": "Singhadurbarnews",
    "profiles_matched": [
      "Election Monitoring"
    ],
    "keywords_matched": [
      "निर्वाचन"
    ],
    "snippet": "नाडाको नवनिर्वाचित अध्यक्षलाई पदभार हस्तान्तरण तथा सपथ ग्रहण सम्पन्न\nवि.सं.२०८२ फागुन २८ बिहीवार\nshares\nकाठमाडौं । नाडा अटोमोवाइल्स एशोसिएशन अफ नेपाल (नाडा) को केन्द्रीय कार्यसमितिको पहिलो बैठकमा नाडाका निवर्तमान अध्यक्ष करण चौधरीले नवनिर्वाचित अध्यक्ष सुरेन्द्रकुमार उप्रेतीलाई आफ्नो पदभार विधिवत रूपमा हस्तान्तरण गरेका छन् ।\nसो अवसरमा निवर्तमान अध्यक्ष चौधरीले नवनिर्वाचित अध्यक्ष उप्रेतीलाई सफल कार्यकालको शुभकामना व्यक्त गर्दै नाडाको संस्थागत विकास तथा अटोमोबाइल क्षेत्रको उन्नयनमा उहाँको नेतृत्व",
    "content": "नाडाको नवनिर्वाचित अध्यक्षलाई पदभार हस्तान्तरण तथा सपथ ग्रहण सम्पन्न\nवि.सं.२०८२ फागुन २८ बिहीवार\nshares\nकाठमाडौं । नाडा अटोमोवाइल्स एशोसिएशन अफ नेपाल (नाडा) को केन्द्रीय कार्यसमितिको पहिलो बैठकमा नाडाका निवर्तमान अध्यक्ष करण चौधरीले नवनिर्वाचित अध्यक्ष सुरेन्द्रकुमार उप्रेतीलाई आफ्नो पदभार विधिवत रूपमा हस्तान्तरण गरेका छन् ।\nसो अवसरमा निवर्तमान अध्यक्ष चौधरीले नवनिर्वाचित अध्यक्ष उप्रेतीलाई सफल कार्यकालको शुभकामना व्यक्त गर्दै नाडाको संस्थागत विकास तथा अटोमोबाइल क्षेत्रको उन्नयनमा उहाँको नेतृत्व महत्वपूर्ण हुने विश्वास व्यक्त गरे ।\nयसै अवसरमा नवनिर्वाचित अध्यक्ष सुरेन्द्रकुमार उप्रेतीले पद तथा गोपनीयताको सपथ ग्रहण गर्दै आफ्नो कार्यकालमा नाडाको उद्देश्य, विधान तथा मूल्य मान्यताहरू अनुरूप संस्थालाई अझ सशक्त, सक्रिय तथा प्रभावकारी बनाउने प्रतिबद्धता व्यक्त गरे ।\nउनले सम्पूर्ण सदस्य व्यवसायीहरूको हित संरक्षण, अटोमोबाइल क्षेत्रको विकास तथा सम्बन्धित सरोकारवाला निकायहरूसँग सहकार्य गर्दै अघि बढ्ने धारणा व्यक्त गरे ।\nउक्त बैठककै क्रममा नाडाका नवनिर्वाचित अध्यक्ष सुरेन्द्रकुमार उप्रेतीले नाडा विधान २०७८ को दफा २०.१ को ‘ङ’ बमोजिम श्री महेश पाल, श्री दीपककुमार अग्रवाल तथा राजेश गिरीलाई नाडाको केन्द्रीय कार्यसमितिको सदस्य पदमा मनोनयन गरेका छन् । उनले मनोनित सदस्यहरूलाई स्वागत गर्दै संस्थाको आगामी गतिविधिहरूमा सक्रिय भूमिका निर्वाह गर्ने अपेक्षा व्यक्त गरेका छन् ।\nसाथै, नाडाको केन्द्रीय कार्यसमितिले निकट भविष्यमै पदाधिकारीहरूको चयनका लागि निर्वाचन प्रक्रिया सम्पन्न गर्ने निर्णय समेत गरेको छ। आगामी दिनहरूमा नाडाले अटोमोबाइल क्षेत्रको समग्र विकास, व्यवसायीहरूको हकहित संरक्षण तथा नीतिगत सहकार्यलाई थप सुदृढ गर्दै अघि बढ्ने विश्वास व्यक्त गरेका छन् ।",
    "images": [
      "https://singhadurbarnews.com/wp-content/themes/singhdurbarnews_theme/images/logo.png",
      "https://singhadurbarnews.com/wp-content/themes/singhdurbarnews_theme/images/logo.png",
      "https://singhadurbarnews.com/wp-content/themes/singhdurbarnews_theme/images/logo.png",
      "https://singhadurbarnews.com/wp-content/themes/singhdurbarnews_theme/images/icon.jpg",
      "https://singhadurbarnews.com/wp-content/uploads/2026/03/photo-2_c9def0ab-scaled.jpg",
      "https://singhadurbarnews.com/wp-content/uploads/2025/12/civil-hospital.gif",
      "https://singhadurbarnews.com/wp-content/uploads/2025/08/WhatsAppVideo2025-11-10at5.35.46PM-ezgif.com-video-to-gif-converter.gif",
      "https://singhadurbarnews.com/wp-content/uploads/2026/03/FB_IMG_1772973192675-312x224.jpg",
      "https://singhadurbarnews.com/wp-content/uploads/2026/03/file_00000000b04471fa87b0aaab9d446e62-312x224.png",
      "https://singhadurbarnews.com/wp-content/uploads/2026/03/file_000000004cf871fa80475ec58a8c018f-312x224.png"
    ]
  },
  {
    "url": "https://www.makalukhabar.com/2026/03/99977573982/",
    "title": "समानुपातिकतर्फको सिट सङ्ख्या सार्वजनिक, कसले कति पाए ?",
    "pub_date": "2026-03-12 21:42:59",
    "fetched_at": "2026-03-12T16:17:45.170258+00:00",
    "portal": "Makalukhabar",
    "profiles_matched": [
      "Election Monitoring"
    ],
    "keywords_matched": [
      "निर्वाचन",
      "कांग्रेस",
      "मतदान",
      "निर्वाचन आयोग",
      "मतगणना"
    ],
    "snippet": "समानुपातिकतर्फको सिट सङ्ख्या सार्वजनिक, कसले कति पाए ?\nकाठमाडौँ । निर्वाचन आयोगले समानुपातिकतर्फ निर्वाचित हुने गरी दलले प्राप्त गर्ने सिट सङ्ख्या निर्धारण गरी सार्वजनिक गरेको छ ।\nआयोगले आज विज्ञप्ति जारी गरी समानुपातिक निर्वाचन प्रणालीतर्फको सम्पूर्ण मतगणना सम्पन्न गरी प्रतिनिधिसभा सदस्य निर्वाचन ऐन, २०७४ को दफा ६०(२) अनुसार सम्बन्धित दलहरुले प्राप्त गरेको कूल सदर मत सङ्ख्याका आधारमा प्रचलित निर्वाचन कानुन बमोजिम तोकिएको थ्रेसहोल्ड (तीन प्रतिशत) पार गर्ने देहायका ६ दलबाट निम्नानुसारको सङ्ख्यामा",
    "content": "समानुपातिकतर्फको सिट सङ्ख्या सार्वजनिक, कसले कति पाए ?\nकाठमाडौँ । निर्वाचन आयोगले समानुपातिकतर्फ निर्वाचित हुने गरी दलले प्राप्त गर्ने सिट सङ्ख्या निर्धारण गरी सार्वजनिक गरेको छ ।\nआयोगले आज विज्ञप्ति जारी गरी समानुपातिक निर्वाचन प्रणालीतर्फको सम्पूर्ण मतगणना सम्पन्न गरी प्रतिनिधिसभा सदस्य निर्वाचन ऐन, २०७४ को दफा ६०(२) अनुसार सम्बन्धित दलहरुले प्राप्त गरेको कूल सदर मत सङ्ख्याका आधारमा प्रचलित निर्वाचन कानुन बमोजिम तोकिएको थ्रेसहोल्ड (तीन प्रतिशत) पार गर्ने देहायका ६ दलबाट निम्नानुसारको सङ्ख्यामा उम्मेदवार निर्वाचित हुने गरी दलले प्राप्त गर्ने सिट सङ्ख्या निर्धारण भएको जनाएको छ ।\nराष्ट्रिय स्वतन्त्र पार्टीले ५७ सिट, नेपाली कांग्रेसले २०, नेपाल कम्युनिष्ट पार्टी (एकीकृत माक्र्सवादी–लेनिनवादी)ले १६, नेपाली कम्युनिष्ट पार्टीले नौ तथा श्रम संस्कृति पार्टीले र राष्ट्रिय प्रजातन्त्र पार्टीले चार÷चार सिट प्राप्त गरेका छन् ।\nसमानुपातिक निर्वाचन प्रणालीतर्फको सम्पूर्ण मतगणना सम्पन्न भई प्रतिनिधिसभा सदस्य निर्वाचन ऐन, २०७४ को दफा ६० अनुसार आयोगको आजको निर्णय बमोजिम सिट बाँडफाँटसमेत गरिएको हो ।\nप्रतिनिधिसभा सदस्य निर्वाचन, २०८२ मा कूल एक करोड ८९ लाख ३ हजार ६८९ मतदातामध्ये पहिलो हुने निर्वाचित हुने निर्वाचन प्रणालीतर्फ एक करोड ११ लाख ६८ हजार ३२ जनाले मतदान गरेका र त्यसमध्ये एक करोड ५ लाख ५९ हजार १७ (९४.५५%) मत सदर भएको छ । त्यस्तै समानुपातिक निर्वाचन प्रणालीतर्फ एक करोड १२ लाख ८० हजार ६१७ जनाले मतदान गरेकामा एक करोड ८ लाख ३५ हजार २५ (९६.०५%) मत सदर भएको छ ।\nउल्लिखित सिट सङ्ख्याअनुसार ऐनको दफा ६०(४), प्रतिनिधिसभा सदस्य निर्वाचन नियमावली, २०७४ को नियम ४१ तथा प्रतिनिधिसभा सदस्य समानुपातिक निर्वाचन निर्देशिका, २०८२ को दफा ३५ बमोजिम तीन दिनभित्र उम्मेदवारको नाम छनोट गरी आयोगसमक्ष पेस गर्न सम्बन्धित राजनीतिक दललाई आजै पत्राचार गरिएको आयोगले जनाएको छ ।",
    "images": [
      "https://certify.alexametrics.com/atrk.gif?account=dk25x1sq3P20YM",
      "https://www.makalukhabar.com/wp-content/themes/makalukhabar-2021/assets/img/twitter.png",
      "https://www.makalukhabar.com/wp-content/themes/makalukhabar-2021/assets/img/tik-tok.png",
      "https://www.makalukhabar.com/wp-content/uploads/2024/12/makalu-logo.png",
      "https://www.makalukhabar.com/wp-content/uploads/2026/01/Tiago-EV-EMI-mk.jpg",
      "https://www.makalukhabar.com/wp-content/uploads/2026/01/tata-mk.jpg",
      "https://www.makalukhabar.com/wp-content/uploads/2023/10/Final-icon-Logo-2023.png",
      "https://www.makalukhabar.com/wp-content/uploads/2026/03/samanu-MK.png",
      "https://www.makalukhabar.com/wp-content/uploads/2021/03/national-life-makalu-khabar.gif",
      "https://www.makalukhabar.com/wp-content/uploads/2021/03/national-life-makalu-khabar.gif"
    ]
  },
  {
    "url": "https://farakdhar.com/story/163437",
    "title": "निर्वाचन खर्च सार्वजनिक गर्न आयोगको अनुरोध, नबुझाए कारबाही हुने",
    "pub_date": "2026-03-12 21:42:48",
    "fetched_at": "2026-03-12T16:17:51.359260+00:00",
    "portal": "Farakdhar",
    "profiles_matched": [
      "Election Monitoring"
    ],
    "keywords_matched": [
      "निर्वाचन",
      "निर्वाचन आयोग"
    ],
    "snippet": "निर्वाचन आयोगले उम्मेदवारलाई आफ्नो निर्वाचन खर्च विवरण बुझाउन अनुरोध गरेको छ । आयोगले बिहीबार विज्ञप्ति जारी गरी निर्वाचन सम्पन्न भएको मितिले ३५ दिनभित्र राजनीतिक दलले निर्वाचन आयोगमा र उम्मेदवारले आफ्नो जिल्लामा रहेको प्रदेश/जिल्ला निर्वाचन कार्यालयमा निर्वाचन प्रचारप्रसारमा भएको आम्दानी तथा खर्चको विवरण तथा सो विवरण सार्वजनिक गरेको जानकारी गराउन अनुरोध गरेको हो ।\nआफ्नो जिल्लामा रहेको प्रदेश/जिल्ला निर्वाचन कार्यालयको सूचना पाटी, सम्बन्धित गाउँपालिका वा नगरपालिका वा वडा कार्यालयको सूचना पाटी, र",
    "content": "निर्वाचन आयोगले उम्मेदवारलाई आफ्नो निर्वाचन खर्च विवरण बुझाउन अनुरोध गरेको छ । आयोगले बिहीबार विज्ञप्ति जारी गरी निर्वाचन सम्पन्न भएको मितिले ३५ दिनभित्र राजनीतिक दलले निर्वाचन आयोगमा र उम्मेदवारले आफ्नो जिल्लामा रहेको प्रदेश/जिल्ला निर्वाचन कार्यालयमा निर्वाचन प्रचारप्रसारमा भएको आम्दानी तथा खर्चको विवरण तथा सो विवरण सार्वजनिक गरेको जानकारी गराउन अनुरोध गरेको हो ।\nआफ्नो जिल्लामा रहेको प्रदेश/जिल्ला निर्वाचन कार्यालयको सूचना पाटी, सम्बन्धित गाउँपालिका वा नगरपालिका वा वडा कार्यालयको सूचना पाटी, राजनीतिक दलको जुनसुकै तहको कार्यालय वा वेबसाइट (राजनीतिक दलको तर्फबाट उम्मेदवार भएका उम्मेदवारको हकमा), आमसञ्चार माध्यम (पत्रपत्रिका, रेडियो, टेलिभिजन आदि) वा सामाजिक सञ्जाल (फेसबुक, ट्विटर, इन्स्टाग्राम आदि) मा आफ्नो निर्वाचन विवरण सार्वजनिक गर्न आयोगको अनुरोध छ ।\nनिर्वाचन खर्चको विवरण नबुझाउने तथा सार्वजनिक नगर्ने एवं निर्वाचन खर्चको विवरण सार्वजनिक गरी त्यसरी सार्वजनिक गरेको विवरणको प्रमाणसहित लिखित जानकारी आयोग तथा सम्बन्धित निर्वाचन कार्यालयमा नदिने राजनीतिक दल तथा उम्मेदवारको हकमा निर्वाचन (कसुर तथा सजाय) ऐन, २०७३ को दफा ३१ बमोजिम कारबाही हुने आयोगले जनाएको छ।\nनिर्वाचन ऐन, २०७४ को दफा ७२ को उपदफा (४) बमोजिम निर्वाचन प्रचार प्रसारमा गरेको खर्चको विवरण पहिलो हुने निर्वाचित हुने प्रणालीतर्फ उम्मेदवारले सम्बन्धित जिल्ला निर्वाचन कार्यालयमा र समानुपातिक निर्वाचन प्रणालीतर्फको हकमा सम्बन्धित राजनीतिक दलले निर्वाचन आयोगसमक्ष तोकिएको ढाँचामा निर्वाचन प्रचारप्रसारमा भएको आम्दानी र खर्चको विवरण सार्वजनिक गर्नु भनिएको छ।\nनिर्वाचन (कसुर तथा सजाय) ऐन, २०७३ को दफा ३१ को उपदफा (२) बमोजिम खर्चको विवरण सम्बन्धित सबैको जानकारीको लागि आयोगले तोके बमोजिम सार्वजनिक गर्नुपर्नेछ भन्ने कानुनी व्यवस्था छ।\nफरकधारमा प्रकाशित कुनै समाचारमा तपाईंको गुनासो भए हामीलाई [email protected] मा इमेल गर्न सक्नुहुनेछ । यही इमेलमा तपाईंले आफ्नो विचार वा विश्लेषण, सल्लाह र सुझाव पनि पठाउन सक्नुहुनेछ । हामीसँग तपाईं फेसबुक, ट्विटर, इन्स्टाग्राम, युट्युबमा पनि जोडिन सक्नुहुन्छ ।",
    "images": [
      "https://certify.alexametrics.com/atrk.gif?account=K32Gs1DTcA20Ug",
      "https://fdcdn.prixacdn.net/media/albums/logo_fd_icByRp1WFp.png",
      "https://fdcdn.prixacdn.net/static/assets/images/farakdhar-logo4.png",
      "https://fdcdn.prixacdn.net/media/albums/logo_fd_icByRp1WFp.png",
      "https://fdcdn.prixacdn.net/media/albums/logo_fd_icByRp1WFp.png",
      "https://fdcdn.prixacdn.net/media/albums/logo_fd_icByRp1WFp.png",
      "https://fdcdn.prixacdn.net/media/albums/fd_pkaLV4MyIb.png",
      "https://fdcdn.prixacdn.net/media/albums/Nirbachan_Ayog_I5TEYtDKyt.jpg",
      "https://fdcdn.prixacdn.net/media/EVEREST_COLLEGE_1_25tgU4qzW3.gif",
      "https://fdcdn.prixacdn.net/media/EDF_Admissions_Google_Ad.gif"
    ]
  },
  {
    "url": "https://www.kathmandupati.com/news/iran-31/401938/",
    "title": "होर्मुज मार्ग बन्द गर्ने इरानको धम्की, युरोपेली ऊर्जा बजारमा धक्का",
    "pub_date": "2026-03-12 21:42:24",
    "fetched_at": "2026-03-12T16:17:55.603528+00:00",
    "portal": "Kathmandupati",
    "profiles_matched": [],
    "keywords_matched": [],
    "snippet": "एजेन्सी – विश्वको सबैभन्दा महत्त्वपूर्ण तेल मार्गमध्ये एक होर्मुज जलडमरू (स्ट्रेट अफ होर्मुज) बन्द गर्ने इरानको धम्कीले युरोपेली ऊर्जा बजारहरूमा धक्का दिएको छ ।\nजसका कारण जर्मनीमा पेट्रोलको मूल्य प्रतिलिटर २.३० युरोभन्दा माथि पुगेको छ भने डिजेलको मूल्य अझ बढेको छ ।\nखाडी र ओमानको बिचमा अवस्थित होर्मुज जलडमरूम खाडीबाट खुला महासागरमा जाने एक मात्र समुद्री मार्ग हो । यसले विश्वव्यापी समुद्री तेल ढुवानीको लगभग एक चौथाई भागका साथै ठूलो मात्रामा तरल प्राकृतिक ग्यास र मलहरू ह्यान्डल गर्दछ ।\nथोक ऊर्जा झट",
    "content": "एजेन्सी – विश्वको सबैभन्दा महत्त्वपूर्ण तेल मार्गमध्ये एक होर्मुज जलडमरू (स्ट्रेट अफ होर्मुज) बन्द गर्ने इरानको धम्कीले युरोपेली ऊर्जा बजारहरूमा धक्का दिएको छ ।\nजसका कारण जर्मनीमा पेट्रोलको मूल्य प्रतिलिटर २.३० युरोभन्दा माथि पुगेको छ भने डिजेलको मूल्य अझ बढेको छ ।\nखाडी र ओमानको बिचमा अवस्थित होर्मुज जलडमरूम खाडीबाट खुला महासागरमा जाने एक मात्र समुद्री मार्ग हो । यसले विश्वव्यापी समुद्री तेल ढुवानीको लगभग एक चौथाई भागका साथै ठूलो मात्रामा तरल प्राकृतिक ग्यास र मलहरू ह्यान्डल गर्दछ ।\nथोक ऊर्जा झट्काले जर्मन उपभोक्ताहरूलाई पहिले नै असर गरिरहेको छ, इन्धन लागतले दैनिक बजेटमा ठूलो प्रभाव पारेको छ ।\n‘गत हप्ता, जब मैले यसलाई सुरुबाट भरें, यसको मूल्य लगभग असी यूरो थियो । अब यो ६७ यूरो भएको छ । तर यो केवल आधा ट्यांकी हो,’ जर्मन चालक कादिर ओज्टर्कले भने ।\nऊर्जा विश्लेषकहरूले उपभोक्ता मूल्यवृद्धि समयपूर्व हुन सक्ने चेतावनी दिएका छन् । म्युनिखको प्राविधिक विश्वविद्यालयका प्राध्यापक स्वेतलाना इकोनिकोभाले आपूर्ति शृंखलाका धेरै तहहरूमा प्रशस्त इन्भेन्टरीहरू रहेको बताइन् ।\nजर्मनीमा, ऊर्जा कर र कार्बन डाइअक्साइड लेवी जस्ता करहरूले ग्यास र डिजेलको मूल्यमा उल्लेखनीय प्रभाव पार्ने पनि देखिएको छ । उपभोक्ताहरूले इन्धनमा १९ प्रतिशत मूल्य अभिवृद्धि कर पनि तिर्छन् । बाँकीले तेल उद्योगको लागत र मार्जिन र कच्चा तेलको अन्तर्निहित मूल्यलाई प्रतिबिम्बित गर्दछ ।\nयद्यपि युरोपको तेल आपूर्ति अहिलेको लागि सुरक्षित छ । हर्मुजको जलडमरूबाट गुज्रने ऊर्जा स्रोतहरूमा अवरोधहरूले विश्वव्यापी बजारहरूमा तरंग ल्याउन सक्छ । जसले गर्दा द्वन्द्व बढ्यो भने मूल्यहरू अझ उच्च हुन सक्नेछ ।\nफेब्रुअरी २८ मा संयुक्त राज्य अमेरिका र इजरायलले इरानमा ठूलो मात्रामा संयुक्त हवाई आक्रमण सुरु गरेपछि मध्यपूर्वमा तनाव तीव्र गतिमा बढिरहेको छ । इरानी पक्षले इजरायल र अमेरिकी सम्पत्तिलाई लक्षित गर्दै यस क्षेत्रभरि धेरै क्षेप्यास्त्र र ड्रोन आक्रमणहरू गरिरहेका छन् । जसले खाडीका धेरै देशहरूलाई असर गरेको छ ।\nसैन्य टकरावले ऊर्जा संकटको डर थप बढेर गएको छ । हर्मुज जलडमरू अवरोधको जोखिमले युरोपमा इन्धन र ग्यास आपूर्तिमा थप झट्का लाग्ने संकेत गरिएको छ । (सीसीटीभीप्लस)\nप्रतिक्रिया",
    "images": [
      "https://www.kathmandupati.com/wp-content/themes/kathmandupatinaya/img/logo.png",
      "https://www.kathmandupati.com/wp-content/themes/kathmandupatinaya/img/logo.png",
      "https://www.kathmandupati.com/wp-content/uploads/2025/09/Gif-for-kathmandupati.gif",
      "https://www.kathmandupati.com/wp-content/uploads/2026/03/ur.jpg",
      "https://www.kathmandupati.com/wp-content/uploads/2024/06/ktmpati.png",
      "https://www.kathmandupati.com/wp-content/uploads/2024/09/latest.gif",
      "https://www.kathmandupati.com/wp-content/uploads/2026/03/ur-150x150.jpg",
      "https://www.kathmandupati.com/wp-content/uploads/2024/08/RPP-Party-office-150x150.jpg",
      "https://www.kathmandupati.com/wp-content/uploads/2025/11/Election-Commission-EC1659856638-150x150.jpeg",
      "https://www.kathmandupati.com/wp-content/uploads/2024/12/300-by-200-.gif"
    ]
  },
  {
    "url": "https://gorkhapatraonline.com/news/196171",
    "title": "केपीएल प्रतियोगिताः उद्घाटन खेलमा युनाइटेड भिजन र कोहलपुर स्पोर्टस विजयी",
    "pub_date": "2026-03-12 22:14:23",
    "fetched_at": "2026-03-12T16:33:08.875237+00:00",
    "portal": "Gorkhapatraonline",
    "profiles_matched": [],
    "keywords_matched": [],
    "snippet": "गजेन्द्र गुरुङ\nखजुरा, फागुन २८ गते । ‘क्याम्पा’ कोहलपुर प्राइड लिग (केपीएल) राष्ट्रिय टि–२० क्रिकेट प्रतियोगिताको पहिलो दिन उद्घाटन खेलमा युनाइटेड भिजन क्रिकेट क्लब र कोहलपुर स्पोर्टस एकेडेमीले विजयी सुरुवात गरेका छन् ।\nप्रतियोगिताको पहिलो दिनको प्रतियोगितामा युनाइटेड भिजन क्रिकेट क्लबले ब्राइटल्याण्ड स्कुल र कोहलपुर स्पोर्टस एकेडेमीले हिमालयन क्रिकेट एकेडेमीलाई हराउँदै विजयी सुरुवात गरेका हुन् ।\nपहिलो उद्घाटन खेलमा युनाइटेड भिजन क्रिकेट क्लबले टस जितेर ब्राइटल्याण्ड स्कुललाई बलिङको निम्तो दिएको",
    "content": "गजेन्द्र गुरुङ\nखजुरा, फागुन २८ गते । ‘क्याम्पा’ कोहलपुर प्राइड लिग (केपीएल) राष्ट्रिय टि–२० क्रिकेट प्रतियोगिताको पहिलो दिन उद्घाटन खेलमा युनाइटेड भिजन क्रिकेट क्लब र कोहलपुर स्पोर्टस एकेडेमीले विजयी सुरुवात गरेका छन् ।\nप्रतियोगिताको पहिलो दिनको प्रतियोगितामा युनाइटेड भिजन क्रिकेट क्लबले ब्राइटल्याण्ड स्कुल र कोहलपुर स्पोर्टस एकेडेमीले हिमालयन क्रिकेट एकेडेमीलाई हराउँदै विजयी सुरुवात गरेका हुन् ।\nपहिलो उद्घाटन खेलमा युनाइटेड भिजन क्रिकेट क्लबले टस जितेर ब्राइटल्याण्ड स्कुललाई बलिङको निम्तो दिएको थियो । सुरुवाती ब्याटिङ गरेको युनाइटेड भिजन क्रिकेट क्लबले निर्धारित २० ओभरमा ८ विकेट गुमाउँदै १ सय ५५ रन बनायो ।\nयुनाइटेडले दिएको १ सय ५६ रनको लक्ष्य पछ्याएको ब्राइटल्याण्ड स्कुलले १६.१ ओभरमा अलआउट हुँदै १ सय १ रनमा समेटियो । योसँगै युनाइटेड २२ रनले विजयी भएको हो । युनाइटेडलाई विजयी गराउन महत्वपूर्ण ३ विकेट लिँदै सन्तोष यादव ‘प्लेयर अफ द म्याच’ घोषित भए ।\nयस्तै प्रतियोगिताको दोस्रो खेल कोहलपुर स्पोर्टस एकेडेमी र हिमालयन क्रिकेट एकेडेमीबीच प्रतिस्पर्धा भएको थियो । टस जितेको कोहलपुर स्पोर्टस एकेडेमीले पहिला ब्याटिङ गर्ने निर्णय ग¥यो ।\nकोहलपुर स्पोर्टस एकेडेमीले सुरुवाती ब्याटिङ गर्दै निर्धारित २० ओभरमा ६ विकेट गुमाउँदै १ सय ९७ रन बनाएको थियो । अर्जुन घर्तीले २७ बलमा ६५ रन र भीम सार्कीले ३७ बलमा ५२ रनको अर्धशतक पारीको सहयोगमा कोहलपुर स्पोर्टस एकेडेमीले हिमालयन क्रिकेट एकेडेमीलाई विसाल १ सय ९८ रनको लक्ष्य दिएको थियो ।\nकोहलपुर स्पोर्टस एकेडेमीले दिएको १ सय ९८ रनको विशाल लक्ष्य पछ्याएको हिमालयन क्रिकेट एकेडेमीले खराब सुरुवात गर्दै ७५ रनमा अलआउट भयो । निर्धारित १६.३ ओभरमा अलआउट हुँदै ७५ रन जोडेर १ सय २२ रनको हार ब्यहोर्नु प¥यो ।\nटिमका लागि कुनै पनि ब्याटरले ठूलो साझेदारी बनाउन सकेनन् । हिमालयन क्रिकेट एकेडेमीका ब्याटरहरु कोहलपुर स्पोर्टस एकेडेमीका बलरसामु निरीह बने । कोहलपुर स्पोर्टस एकेडेमीलाई विजयी बनाउन महत्वपूर्ण ४ विकेट लिएका शिद्धान्तराज शाही ‘प्लेयर अफ द म्याच’ घोषित भए ।\nप्रतियोगिताका मिडिया कोअर्डिनेटर सञ्जय मण्डलले प्रथम हुने टिमले नगद चार लाख, शिल्ड, मेडल र प्रमाणपत्र प्राप्त गर्ने जानकारी दिनुभयो । त्यसैगरी द्वितीय हुने टिमलाई नगद दुई लाख तथा शिल्ड, मेडल र प्रमाणपत्र प्राप्त गर्नेछन् भने बेस्ट ब्याटर र बेस्ट बलरले क्रमशः १०-१० हजार रुपियाँ नगद प्राप्त गर्नेछन् ।\nप्रतियोगिताका डाइरेक्टर विनायक गिरीले बिहीबार दिउँसो एक औपचारिक कार्यक्रमबिच नेपाल क्रिकेट सङ्घ (क्यान)का सेक्रेटरी पारस खड्काले प्रतियोगिताको उद्घाटन गर्नुभएको जानकारी दिनुभयो ।\nकोहलपुर नगरपालिका वडा नम्बर ११ स्थित कोहलपुर क्रिकेट रङ्गशालामा बिहीबारदेखि सञ्चालन भएको प्रतियोगिताको संरक्षक कोहलपुर नगरपालिका रहेको छ । बाँके जिल्ला क्रिकेट सङ्घको समन्वय र कोहलपुर क्रिकेट स्पोर्टस एकेडेमी कोहलपुरको आयोजनामा प्रतियोगिता सञ्चालन भइरहेको हो । विभिन्न ६ वटा टिम समावेश रहेको प्रतियोगिता आगामी चैत २ गतेसम्म सञ्चालन हुने छ ।",
    "images": [
      "https://gorkhapatraonline.com/storage/media/311657/gp-logo-black.svg",
      "https://gorkhapatraonline.com/storage/media/311657/gp-logo-black.svg",
      "https://gorkhapatraonline.com/commons/header-icons/trn.png",
      "https://gorkhapatraonline.com/commons/header-icons/muna.png",
      "https://gorkhapatraonline.com/commons/header-icons/madhupark.png",
      "https://gorkhapatraonline.com/commons/header-icons/yuba-manch.png",
      "https://gorkhapatraonline.com/commons/header-icons/naya-nepal.png",
      "https://gorkhapatraonline.com/storage/media/343091/Untitled-1.jpg",
      "https://gorkhapatraonline.com/storage/media/146779/conversions/gopa-thumb.jpg",
      "https://gorkhapatraonline.com/storage/media/146779/conversions/gopa-thumb.jpg"
    ]
  },
  {
    "url": "https://nepalnews.com/2026/03/12/insect-infestation-in-corn-crop-farmers-worried/",
    "title": "मकै बालीमा किराको प्रकोप, किसान चिन्तित",
    "pub_date": "2026-03-12 22:13:36",
    "fetched_at": "2026-03-12T16:33:13.872913+00:00",
    "portal": "Nepalnews",
    "profiles_matched": [],
    "keywords_matched": [],
    "snippet": "सुनसरी। सुनसरी सदरमुकाम इनरुवा सहित जिल्लाका बिभिन्न स्थानमा लगाएको मकै बालीमा रोग किराको प्रकोपको प्रकोप बढेको छ ।\nइनरुवा सहित रामधुनी, हरिनगर, देवानगञ्ज, बर्जु, गढी र भोक्राहा नरसिंह गाउँपालिका लगायतका स्थानमा लगाइएको मकै बालीमा फौजी किरा देखिएको इनरुवा–९ बबियाका शिबनारायण यादबले बताए ।\nमकै बालीमा रोगकिरा देखिन थालेपछि विषादी छर्न बाध्य भएको उनले बताए । केही गोड्ने बेला र केही गोडिसकेका मकै कीराले खाएर नष्ट गरेपछि विषादी छर्नका लागि बाध्य भएको उनले बताए । नहरमा पानी नभएर समस्यामा परेका किसानला",
    "content": "सुनसरी। सुनसरी सदरमुकाम इनरुवा सहित जिल्लाका बिभिन्न स्थानमा लगाएको मकै बालीमा रोग किराको प्रकोपको प्रकोप बढेको छ ।\nइनरुवा सहित रामधुनी, हरिनगर, देवानगञ्ज, बर्जु, गढी र भोक्राहा नरसिंह गाउँपालिका लगायतका स्थानमा लगाइएको मकै बालीमा फौजी किरा देखिएको इनरुवा–९ बबियाका शिबनारायण यादबले बताए ।\nमकै बालीमा रोगकिरा देखिन थालेपछि विषादी छर्न बाध्य भएको उनले बताए । केही गोड्ने बेला र केही गोडिसकेका मकै कीराले खाएर नष्ट गरेपछि विषादी छर्नका लागि बाध्य भएको उनले बताए । नहरमा पानी नभएर समस्यामा परेका किसानलाई मकैंमा रोग किराको संक्रमणले झनै चिन्तित बनाएको किसान शम्भु यादवले गुनासो गरे ।\nमकै बालीबाट राम्रो आम्दानी लिने सोचका साथी खेती गरेको भएपनि फौजी किराको आक्रमणले सोचे अनुसारको आम्दनी हुने की नहुने चिन्ताले सताएको किसान लक्ष्मण मेहताले बताए ।\nजिल्लामा यस बर्ष १२ हजार ६३ हेक्टर क्षेत्रफलमा मकै खेती भएको कृषि ज्ञान केन्द्र इनरुवा सुनसरीका प्रमुख निलकमल सिंहले जानकारी दिए ।",
    "images": [
      "https://english.nepalnews.com/wp-content/uploads/2025/01/Nepal-news-white.png",
      "https://english.nepalnews.com/wp-content/uploads/2025/01/Nepal-news-white.png",
      "https://english.nepalnews.com/wp-content/uploads/2025/01/close.png",
      "https://english.nepalnews.com/wp-content/uploads/2025/01/direct-flight.png",
      "https://english.nepalnews.com/wp-content/uploads/2025/01/cloudy-day.png",
      "https://english.nepalnews.com/wp-content/uploads/2025/01/air-quality.png",
      "https://english.nepalnews.com/wp-content/uploads/2025/01/change.png",
      "https://english.nepalnews.com/wp-content/uploads/2025/01/gold.png",
      "https://nepalnews.com/wp-content/uploads/2025/08/favicon-01.png",
      "https://nepalnews.com/wp-content/uploads/2026/03/makai.jpg"
    ]
  },
  {
    "url": "https://hamrakura.com/news-details/209461/2026-03-12",
    "title": "दलहरूको समानुपातिकको सिट सङ्ख्या सार्वजनिक, कसलाई कति ? [विवरणसहित]",
    "pub_date": "2026-03-12 22:08:09",
    "fetched_at": "2026-03-12T16:33:18.485482+00:00",
    "portal": "Hamrakura",
    "profiles_matched": [
      "Election Monitoring"
    ],
    "keywords_matched": [
      "निर्वाचन",
      "कांग्रेस",
      "मतदान",
      "निर्वाचन आयोग",
      "मतगणना"
    ],
    "snippet": "- सुन चाँदी दर\n- विनिमय दर\n- नेपाली पात्रो\n- राशिफल\nकाठमाडौँ । निर्वाचन आयोगले समानुपातिकतर्फ निर्वाचित हुने गरी दलले प्राप्त गर्ने सिट सङ्ख्या निर्धारण गरी सार्वजनिक गरेको छ । आयोगले बिहीबार विज्ञप्ति जारी गरी समानुपातिक निर्वाचन प्रणालीतर्फको सम्पूर्ण मतगणना सम्पन्न गरी प्रतिनिधिसभा सदस्य निर्वाचन ऐन, २०७४ को दफा ६० (२) अनुसार सम्बन्धित दलहरुले प्राप्त गरेको कूल सदर मत सङ्ख्याका आधारमा प्रचलित निर्वाचन कानुन बमोजिम तोकिएको थ्रेसहोल्ड (तीन प्रतिशत) पार गर्ने ६ दलबाट सङ्ख्यामा उम्मेदवार निर्वाचि",
    "content": "- सुन चाँदी दर\n- विनिमय दर\n- नेपाली पात्रो\n- राशिफल\nकाठमाडौँ । निर्वाचन आयोगले समानुपातिकतर्फ निर्वाचित हुने गरी दलले प्राप्त गर्ने सिट सङ्ख्या निर्धारण गरी सार्वजनिक गरेको छ । आयोगले बिहीबार विज्ञप्ति जारी गरी समानुपातिक निर्वाचन प्रणालीतर्फको सम्पूर्ण मतगणना सम्पन्न गरी प्रतिनिधिसभा सदस्य निर्वाचन ऐन, २०७४ को दफा ६० (२) अनुसार सम्बन्धित दलहरुले प्राप्त गरेको कूल सदर मत सङ्ख्याका आधारमा प्रचलित निर्वाचन कानुन बमोजिम तोकिएको थ्रेसहोल्ड (तीन प्रतिशत) पार गर्ने ६ दलबाट सङ्ख्यामा उम्मेदवार निर्वाचित हुने गरी दलले प्राप्त गर्ने सिट सङ्ख्या निर्धारण भएको जनाएको छ ।\nराष्ट्रिय स्वतन्त्र पार्टीले ५७ सिट, नेपाली कांग्रेसले २०, नेकपा एमालेले १६, नेपाली कम्युनिष्ट पार्टीले नौ तथा श्रम संस्कृति पार्टी र राष्ट्रिय प्रजातन्त्र पार्टीले समान चार सिट प्राप्त गरेका छन् ।\nसमानुपातिक निर्वाचन प्रणालीतर्फको सम्पूर्ण मतगणना सम्पन्न भई प्रतिनिधिसभा सदस्य निर्वाचन ऐन, २०७४ को दफा ६० अनुसार आयोगको आजको निर्णय बमोजिम सिट बाँडफाँटसमेत गरिएको हो ।\nप्रतिनिधिसभा सदस्य निर्वाचन, २०८२ मा कूल एक करोड ८९ लाख ३ हजार ६८९ मतदातामध्ये पहिलो हुने निर्वाचित हुने निर्वाचन प्रणालीतर्फ एक करोड ११ लाख ६८ हजार ३२ जनाले मतदान गरेका र त्यसमध्ये एक करोड ५ लाख ५९ हजार १७ (९४.५५ प्रतिशत) मत सदर भएको छ । त्यस्तै समानुपातिक निर्वाचन प्रणालीतर्फ एक करोड १२ लाख ८० हजार ६१७ जनाले मतदान गरेकामा एक करोड ८ लाख ३५ हजार २५ (९६.०५ प्रतिशत) मत सदर भएको छ ।\nउल्लिखित सिट सङ्ख्याअनुसार ऐनको दफा ६० (४), प्रतिनिधिसभा सदस्य निर्वाचन नियमावली, २०७४ को नियम ४१ तथा प्रतिनिधिसभा सदस्य समानुपातिक निर्वाचन निर्देशिका, २०८२ को दफा ३५ बमोजिम तीन दिनभित्र उम्मेदवारको नाम छनोट गरी आयोगसमक्ष पेस गर्न सम्बन्धित राजनीतिक दललाई बिहीबारै पत्राचार गरिएको आयोगले जनाएको छ ।",
    "images": [
      "https://hamrakura.com/uploads/config/frontend/hamrakura-logo.jpg",
      "https://hamrakura.com/frontend/utility/icons/gold-silver.svg",
      "https://hamrakura.com/frontend/utility/icons/money-exchange.svg",
      "https://hamrakura.com/frontend/utility/icons/nepali-calender.svg",
      "https://hamrakura.com/frontend/utility/icons/nepali-horoscope.svg",
      "https://hamrakura.com/uploads/config/frontend/hamrakura-logo.jpg",
      "https://certify.alexametrics.com/atrk.gif?account=LQmzp1IW1d10fn"
    ]
  },
  {
    "url": "https://www.ratopati.com/story/550160/shankar-pokharels-call-dont-be-fooled-by-media-trials",
    "title": "शंकर पोखरेलको आह्वान : मिडिया ट्रायलको  भ्रममा नपर्नुस्",
    "pub_date": "2026-03-12 22:06:27",
    "fetched_at": "2026-03-12T16:33:23.537341+00:00",
    "portal": "Ratopati",
    "profiles_matched": [
      "Election Monitoring"
    ],
    "keywords_matched": [
      "निर्वाचन"
    ],
    "snippet": "शंकर पोखरेलको आह्वान : मिडिया ट्रायलको भ्रममा नपर्नुस्\nसारांश\n- एमाले महासचिव शंकर पोखरेलले पार्टी पङ्क्तिलाई मिडिया ट्रायल र भ्रममा नपर्न आग्रह गरेका छन्।\n- उनले निर्वाचन क्षेत्रको समीक्षा सुरु भइसकेको र आगामी निर्वाचनको समीक्षा गरिने बताए।\n- पोखरेलले पार्टीको आन्तरिक एकतालाई कमजोर बनाउने प्रयास भइरहेको बताए।\nकाठमाडौँ । नेकपा एमालेका महासचिव शंकर पोखरेलले मिडिया ट्रायल र फैलाइएका भ्रममा नपर्न पार्टी पङ्क्तिलाई आग्रह गरेका छन् ।\n‘१६५ वटै निर्वाचन क्षेत्रको निर्वाचन परिणामको समीक्षा कार्य सुरु भइ",
    "content": "शंकर पोखरेलको आह्वान : मिडिया ट्रायलको भ्रममा नपर्नुस्\nसारांश\n- एमाले महासचिव शंकर पोखरेलले पार्टी पङ्क्तिलाई मिडिया ट्रायल र भ्रममा नपर्न आग्रह गरेका छन्।\n- उनले निर्वाचन क्षेत्रको समीक्षा सुरु भइसकेको र आगामी निर्वाचनको समीक्षा गरिने बताए।\n- पोखरेलले पार्टीको आन्तरिक एकतालाई कमजोर बनाउने प्रयास भइरहेको बताए।\nकाठमाडौँ । नेकपा एमालेका महासचिव शंकर पोखरेलले मिडिया ट्रायल र फैलाइएका भ्रममा नपर्न पार्टी पङ्क्तिलाई आग्रह गरेका छन् ।\n‘१६५ वटै निर्वाचन क्षेत्रको निर्वाचन परिणामको समीक्षा कार्य सुरु भइसकेको छ’ उनले फेसबुकमा लेखेका छन्– ‘यो प्रक्रिया पूरा भएपछि आम निर्वाचन २०८२ को समग्र समीक्षा गरिनेछ ।’\nमहासचिव पोखरेलले पार्टीको आन्तरिक एकतालाई कमजोर बनाउने उद्देश्यले केही मिडियामार्फत पार्टी नेताहरूको नाममा भइरहेको मिडिया ट्रायल र फैलाइएका भ्रममा नपर्न सम्पूर्ण पार्टी पङ्क्तिलाई आग्रह गरेका छन् ।\nविगतका गम्भीर सङ्कट र चुनौतीहरूलाई सामना गर्दै हाम्रो पार्टी यहाँसम्म आइपुगेको उल्लेख गर्दै उनले अहिलेका चुनौतीहरूलाई पनि दृढतापूर्वक सामना गर्दै एमाले पुनः थप मजबुत भएर अघि बढ्ने दृढता व्यक्त गरेका छन् ।\nजनतासँगको सम्बन्ध र विश्वास पुनःस्थापित गर्नेतर्फ विशेष जोड दिँदै उनले एकताबद्ध भएर काम गरेमा एमाले सफल हुने उनको दाबी छ ।\nखबर पढेर तपाईलाई कस्तो महसुस भयो ?\nप्रतिक्रिया\nभर्खरै\n-\nशंकर पोखरेलको आह्वान : मिडिया ट्रायलको भ्रममा नपर्नुस्\n-\nजनवरीमा अमेरिकी व्यापार घाटा अपेक्षा गरिएभन्दा बढी\n-\nराहदानी विभागले भन्यो– अन्तरिम अवधिमा सेवा प्रभावित हुन सक्छ\n-\nअमेरिकाले उल्लङ्घन गरेका व्यापार सम्झौताको ‘दृढताका साथ प्रतिक्रिया’ दिइनेः इयु\n-\nमुलुकको राजनीतिक परिवर्तनमा महिलाको योगदान महत्वपूर्ण : पूर्वराष्ट्रपति भण्डारी\n-\nसेतीमा दैनिक सेवा लिने बिरामीको सङ्ख्या बढ्दै",
    "images": [
      "https://www.ratopati.com/build/img/gamepad.png",
      "https://www.ratopati.com/build/img/editor-new.png",
      "https://www.ratopati.com/build/img/keyboard.png",
      "https://www.ratopati.com/build/img/calendar.png",
      "https://npcdn.ratopati.com/media/setting/ratopati-logo_qQKWIp37FR.png",
      "https://www.ratopati.com/build/img/icon-search.png",
      "https://npcdn.ratopati.com/media/news/accident1_0HVVwEUEAJ.jpg",
      "https://npcdn.ratopati.com/media/news/28_LKbWztZouV.jpg",
      "https://npcdn.ratopati.com/media/news/mundum_2MUBe52naH.png",
      "https://rpcdn.ratopati.com/media/albums/matgadana_QLMADztZzv.jpg"
    ]
  },
  {
    "url": "https://www.makalukhabar.com/2026/03/99977573985/",
    "title": "कानूनले मात्र समाज परिवर्तन हुँदैनः पूर्वराष्ट्रपति भण्डारी",
    "pub_date": "2026-03-12 22:02:56",
    "fetched_at": "2026-03-12T16:33:29.128359+00:00",
    "portal": "Makalukhabar",
    "profiles_matched": [],
    "keywords_matched": [],
    "snippet": "कानूनले मात्र समाज परिवर्तन हुँदैनः पूर्वराष्ट्रपति भण्डारी\nकाठमाडौं । पूर्वराष्ट्रपति विद्यादेवी भण्डारीले नेपालको संविधान र कानूनले महिला अधिकारको क्षेत्रमा उल्लेखनीय व्यवस्था गरे पनि समाजमा विद्यमान पितृसत्तात्मक सोच र कुप्रथाका कारण त्यसको व्यावहारिक कार्यान्वयनमा अझै ठूलो चुनौती रहेको बताएकी छन् ।\nमोतिदेवी स्मृति केन्द्रद्वारा बिहीवार आयोजित कार्यक्रमलाई सम्बोधन गर्दै उनले नीतिगत उपलब्धिहरू प्राप्त भए पनि समाजको तल्लो तहसम्म त्यसको अनुभूति हुन नसकेको भन्दै चिन्ता व्यक्त गरिन् ।\nनेपालको संवि",
    "content": "कानूनले मात्र समाज परिवर्तन हुँदैनः पूर्वराष्ट्रपति भण्डारी\nकाठमाडौं । पूर्वराष्ट्रपति विद्यादेवी भण्डारीले नेपालको संविधान र कानूनले महिला अधिकारको क्षेत्रमा उल्लेखनीय व्यवस्था गरे पनि समाजमा विद्यमान पितृसत्तात्मक सोच र कुप्रथाका कारण त्यसको व्यावहारिक कार्यान्वयनमा अझै ठूलो चुनौती रहेको बताएकी छन् ।\nमोतिदेवी स्मृति केन्द्रद्वारा बिहीवार आयोजित कार्यक्रमलाई सम्बोधन गर्दै उनले नीतिगत उपलब्धिहरू प्राप्त भए पनि समाजको तल्लो तहसम्म त्यसको अनुभूति हुन नसकेको भन्दै चिन्ता व्यक्त गरिन् ।\nनेपालको संविधानले महिला समानताको हक, समानुपातिक सहभागिताको हक, प्रजनन स्वास्थ्यसम्बन्धी अधिकार र महिलाविरुद्धको हिंसामा प्रतिवन्ध लगायतका विषयलाई मौलिक हककै रूपमा स्थापित गरेको बताए ।\nआजको आधुनिक युगमा पनि नेपाली समाजमा बालविवाह, बहुविवाह, दाइजो तथा तिलक प्रथा, छाउपडी र बोक्सीको आरोप जस्ता अमानवीय कुपरम्पराहरू कायमै रहनु दुःखद् भएको उनको भनाइ छ । यस्ता गहिरोसँग जरा गाडेका प्रथा, परम्परा र मान्यताहरू केवल कानुन बनाएर मात्र परिवर्तन नहुने कुरामा उनले जोड दिए ।\nमहिलाविरुद्धको हिंसा र विभेद अन्त्य गर्न, लैंगिक समानता प्रवद्र्धन गर्न, महिलाको शैक्षिक तथा आर्थिक सशक्तीकरण गर्न र समाजको समग्र सांस्कृतिक रूपान्तरणका लागि राज्यका सबै निकाय र नागरिक तहबाट एकीकृत प्रयास हुनुपर्नेमा पूर्वराष्ट्रपति भण्डारीले जोड दिए ।",
    "images": [
      "https://certify.alexametrics.com/atrk.gif?account=dk25x1sq3P20YM",
      "https://www.makalukhabar.com/wp-content/themes/makalukhabar-2021/assets/img/twitter.png",
      "https://www.makalukhabar.com/wp-content/themes/makalukhabar-2021/assets/img/tik-tok.png",
      "https://www.makalukhabar.com/wp-content/uploads/2024/12/makalu-logo.png",
      "https://www.makalukhabar.com/wp-content/uploads/2026/01/Tiago-EV-EMI-mk.jpg",
      "https://www.makalukhabar.com/wp-content/uploads/2026/01/tata-mk.jpg",
      "https://www.makalukhabar.com/wp-content/uploads/2023/10/Final-icon-Logo-2023.png",
      "https://www.makalukhabar.com/wp-content/uploads/2026/03/bidya-mk.jpg",
      "https://www.makalukhabar.com/wp-content/uploads/2021/03/national-life-makalu-khabar.gif",
      "https://www.makalukhabar.com/wp-content/uploads/2021/03/national-life-makalu-khabar.gif"
    ]
  },
  {
    "url": "https://corporatekhabar.com/election-364/",
    "title": "आयोगद्वारा निर्वाचन खर्च सार्वजनिक गर्न अनुरोध",
    "pub_date": "2026-03-12 22:02:45",
    "fetched_at": "2026-03-12T16:33:33.815724+00:00",
    "portal": "Corporatekhabar",
    "profiles_matched": [
      "Election Monitoring"
    ],
    "keywords_matched": [
      "निर्वाचन",
      "निर्वाचन आयोग"
    ],
    "snippet": "आयोगद्वारा निर्वाचन खर्च सार्वजनिक गर्न अनुरोध\nकर्पोरट खबर\n10:02 pm, बिहीबार, फाल्गुन २८, २०८२\nकाठमाडौं । निर्वाचन आयोगले उम्मेदवारलाई आफ्नो निर्वाचन खर्च विवरण बुझाउन अनुरोध गरेको छ ।\nआयोगले निर्वाचन सम्पन्न भएको मितिले ३५ दिनभित्र राजनीतिक दलले निर्वाचन आयोगमा र उम्मेदवारले आफ्नो जिल्लामा रहेको प्रदेश÷जिल्ला निर्वाचन कार्यालयमा निर्वाचन प्रचारप्रसारमा भएको आम्दानी तथा खर्चको विवरण तथा सो विवरण सार्वजनिक गरेको जानकारी गराउन अनुरोध गरेको हो ।\nआफ्नो जिल्लामा रहेको प्रदेश-जिल्ला निर्वाचन कार्यालयक",
    "content": "आयोगद्वारा निर्वाचन खर्च सार्वजनिक गर्न अनुरोध\nकर्पोरट खबर\n10:02 pm, बिहीबार, फाल्गुन २८, २०८२\nकाठमाडौं । निर्वाचन आयोगले उम्मेदवारलाई आफ्नो निर्वाचन खर्च विवरण बुझाउन अनुरोध गरेको छ ।\nआयोगले निर्वाचन सम्पन्न भएको मितिले ३५ दिनभित्र राजनीतिक दलले निर्वाचन आयोगमा र उम्मेदवारले आफ्नो जिल्लामा रहेको प्रदेश÷जिल्ला निर्वाचन कार्यालयमा निर्वाचन प्रचारप्रसारमा भएको आम्दानी तथा खर्चको विवरण तथा सो विवरण सार्वजनिक गरेको जानकारी गराउन अनुरोध गरेको हो ।\nआफ्नो जिल्लामा रहेको प्रदेश-जिल्ला निर्वाचन कार्यालयको सूचना पाटी, सम्बन्धित गाउँपालिका वा नगरपालिका वा वडा कार्यालयको सूचना पाटी, राजनीतिक दलको जुनसुकै तहको कार्यालय वा वेवसाइट (राजनीतिक दलको तर्फबाट उम्मेदवार भएका उम्मेदवारको हकमा), आमसञ्चार माध्यम (पत्रपत्रिका, रेडियो, टेलिभिजन आदि) वा सामाजिक सञ्जाल ९फेसबुक, ट्विटर, ईन्स्टाग्राम आदि० मा आफ्नो निर्वाचन विवरण सार्वजनिक गर्न आयोगको अनुरोध छ ।\nनिर्वाचन खर्चको विवरण नबुझाउने तथा सार्वजनिक नगर्ने एवं निर्वाचन खर्चको विवरण सार्वजनिक गरी त्यसरी सार्वजनिक गरेको विवरणको प्रमाणसहित लिखित जानकारी आयोग तथा सम्बन्धित निर्वाचन कार्यालयमा नदिने राजनीतिक दल तथा उम्मेदवारको हकमा निर्वाचन ९कसुर तथा सजाय० ऐन, २०७३ को दफा ३१ बमोजिम कारबाही हुने आयोगले जनाएको छ ।\nनिर्वाचन ऐन, २०७४ को दफा ७२ को उपदफा ९४० बमोजिम निर्वाचन प्रचार प्रसारमा गरेको खर्चको विवरण पहिलो हुने निर्वाचित हुने प्रणालीतर्फ उम्मेदवारले सम्बन्धित जिल्ला निर्वाचन कार्यालयमा र समानुपातिक निर्वाचन प्रणालीतर्फको हकमा सम्बन्धित राजनीतिक दलले निर्वाचन आयोगसमक्ष तोकिएको ढाँचामा निर्वाचन प्रचारप्रसारमा भएको आम्दानी र खर्चको विवरण सार्वजनिक गर्नु भनिएको छ ।\nनिर्वाचन ९कसुर तथा सजाय० ऐन, २०७३ को दफा ३१ को उपदफा (२) बमोजिम खर्चको विवरण सम्बन्धित सबैको जानकारीको लागि आयोगले तोके बमोजिम सार्वजनिक गर्नुपर्नेछ भन्ने कानुनी व्यवस्था छ ।\nFACEBOOK COMMENTS",
    "images": [
      "https://cdn.corporatekhabar.com/uploads/2025/04/corporate.png",
      "https://cdn.corporatekhabar.com/uploads/2025/10/900x150.gif",
      "https://cdn.corporatekhabar.com/uploads/2025/04/corporate.png",
      "https://cdn.corporatekhabar.com/uploads/2024/01/Renu-dahal-bharatpur-metro-150x150.jpg",
      "https://cdn.corporatekhabar.com/uploads/2026/03/dhanraj_mahabir1773215097-150x150.jpg",
      "https://cdn.corporatekhabar.com/uploads/2026/01/Rishi_Dhamala1768872932-150x150.jpg",
      "https://cdn.corporatekhabar.com/uploads/2026/03/dipak_11756116799-150x150.jpg",
      "https://cdn.corporatekhabar.com/uploads/2026/03/DUbe1773247166-150x150.jpg",
      "https://cdn.corporatekhabar.com/uploads/2026/02/Election22.jpg",
      "https://cdn.corporatekhabar.com/uploads/2023/10/National-Life-1.gif"
    ]
  },
  {
    "url": "https://nepalkhabar.com/politics/268335-2026-3-12-22-2-21",
    "title": "रास्वपाले दुई तिहाइ पाउँदा कांग्रेस बन्यो ८४ स्थानमा दोस्रो",
    "pub_date": "2026-03-12 22:02:21",
    "fetched_at": "2026-03-12T16:33:38.204183+00:00",
    "portal": "Nepalkhabar",
    "profiles_matched": [
      "Election Monitoring"
    ],
    "keywords_matched": [
      "चुनाव",
      "निर्वाचन",
      "रास्वपा",
      "कांग्रेस",
      "राप्रपा"
    ],
    "snippet": "फागुन २१ गते सम्पन्न प्रतिनिधि सभा निर्वाचनमा राष्ट्रिय स्वतन्त्र पार्टीले (रास्वपा) करिब दुई तिहाइ सिट जित्दा नेपाली कांग्रेस ३८ सिट खुम्चिएर प्रतिपक्ष कित्तामा पुगेको छ। प्रतिनिधि सभाका १६५ क्षेत्रमध्ये ८४ स्थानमा दोस्रो भएको कांग्रेस ६३ स्थानमा मुख्य प्रतिस्पर्धी बन्न असफल रह्यो।\nयस्तै १८ निर्वाचन क्षेत्रमा भने कांग्रेसको जमानत जफत भएको छ। कांग्रेस उम्मेदवारको झापा २, झापा ३, झापा ५ र सुनसरी १ , सप्तरी १, सप्तरी २, सिराहा ४, महोत्तरी १, महोत्तरी ३, सर्लाही २, सर्लाही ३, रौतहट ३ र बारा ४, काठम",
    "content": "फागुन २१ गते सम्पन्न प्रतिनिधि सभा निर्वाचनमा राष्ट्रिय स्वतन्त्र पार्टीले (रास्वपा) करिब दुई तिहाइ सिट जित्दा नेपाली कांग्रेस ३८ सिट खुम्चिएर प्रतिपक्ष कित्तामा पुगेको छ। प्रतिनिधि सभाका १६५ क्षेत्रमध्ये ८४ स्थानमा दोस्रो भएको कांग्रेस ६३ स्थानमा मुख्य प्रतिस्पर्धी बन्न असफल रह्यो।\nयस्तै १८ निर्वाचन क्षेत्रमा भने कांग्रेसको जमानत जफत भएको छ। कांग्रेस उम्मेदवारको झापा २, झापा ३, झापा ५ र सुनसरी १ , सप्तरी १, सप्तरी २, सिराहा ४, महोत्तरी १, महोत्तरी ३, सर्लाही २, सर्लाही ३, रौतहट ३ र बारा ४, काठमाडाँै ७, काठमाडौँ ८, भक्तपुर १, चितवन ३, रूपन्देही ३ गरी १८ ठाउँमा जमानत जफत भएको छ।\n१६३ क्षेत्रमा उम्मेदवारी दिएको रास्वपाले चुनाव जितेका १२५ स्थानमध्ये ७३ स्थानमा कांग्रेस दोस्रो भएको छ। कांग्रेसले चुनाव जितेका १८ स्थानमध्ये ८ स्थानमा एमाले, ६ स्थानमा नेपाली कम्युनिस्ट पार्टी (नेकपा), २–२ स्थानमा रास्वपा र श्रम संस्कृति पार्टी दोस्रो भएका छन्। ०७९को निर्वाचनमा कांग्रेस प्रत्यक्षमा ५७ र समानुपातिकमा ३२ सहित ८९ सिट जितेर पहिलो दल बनेको थियो। अहिले प्रत्यक्षमा १८ र समानुपातिकमा २० गरी ३८ सिटमा खुम्चिएको छ।\nयस्तै, प्रत्यक्षतर्फ ९ सिटमा खुम्चिएको एमाले उम्मेदवार उठाएको १६४ (मनाङ बाहेक)क्षेत्रमध्ये ४१ स्थानमा दोस्रो भएको छ। रास्वपाले जितेका १२५ सिटमा एमाले २७ स्थानमा दोस्रो बनेको छ। एमालेले जितेका ९ स्थानमध्ये २ ठाउँमा रास्वपा दोस्रो भएको छ। कांग्रेसले जितेका १८ मध्ये ८ र नेकपाले चुनाव जितेका ३ स्थानमा एमाले दोस्रो भएको छ। स्वतन्त्र सांसद महावीर पुनले चुनाव जितेको म्याग्दीमा पनि एमाले दोस्रो बनेको छ। श्रम संस्कृति पार्टीले चुनाव जितेका २ ठाउँमा एमाले दोस्रो बनेको छ।\nएमालेको ४९ क्षेत्रमा एमालेको जमानत जफत भएको छ। ०७९को चुनावमा प्रत्यक्षतर्फ ४४ र समानुपातिकमा ३४ गरी ७८ सिटसहित एमाले दोस्रो भएको थियो। अहिले एमाले प्रत्यक्षमा ९ र समानुपातिकमा १६ गरी २५ सिटमा सीमित भएको छ। यस्तै नेकपा १५ ठाउँमा दोस्रो हुँदा ९९ स्थानमा जमानत जफत भएको छ। प्रत्यक्षतर्फ ८ ठाउँ (धनुषा १) मा चुनाव जितेको नेकपा १७ ठाउँमा दोस्रो भएको छ।\nरास्वपाले चुनाव जितेका १२५ मध्ये १० ठाउँमा नेकपा दोस्रो भएको छ। कांग्रेसले चुनाव जितेका १८ मध्ये ६ ठाउँमा नेकपा दोस्रो बन्दा एमालेले चुनाव जितेको कुनै पनि ठाउँमा नेकपा दोस्रो भएको छैन। ०७९ सालको चुनावमा प्रत्यक्षतर्फ १८ र समानुपातिकमा १४ गरी ३२ सिट ल्याएर तत्कालीन माओवादी तेस्रो बनेको थियो। गत निर्वाचनमा प्रत्यक्षतर्फ १० सिट जितेको तत्कालीन एकीकृत समाजवादी पनि नेकपामा समाहित थियो।\nविभिन्न पार्टी र समूह गरी १९ वटा कम्युनिस्ट घटक मिलेर बनेको नेकपा २०७९ को तत्कालीन माओवादीभन्दा पनि खुम्चिएको छ। नेकपाले अहिले प्रत्यक्षमा ८ र समानुपतिकमा ९ सिट प्राप्त गरेको छ। जितविहीन जसपा ६ ठाउँमा दोस्रो भएको छ। यसअघिको चुनावमा प्रत्यक्षमा ७ र ५ गरी समानुपातिकमा १२ सिट जितेको थियो।\nगत निर्वाचनमा सीके राउत नेतृत्वको जनमत पार्टीले प्रत्यक्षतर्फ १ र समानुपातिकतर्फ ५ गरी ६ सिट हासिल गरेको थियो। समानुपातिकतर्फ थ्रेसहोल्ड नकटाए पनि लोसपाले प्रत्यक्षतर्फ ४ र नागरिक उन्मुक्ति पार्टीले ३ सिट जितेका थिए। थ्रेसहोल्ड पार गर्न नसकेका राष्ट्रिय जनमोर्चा र नेपाल मजदुर किसान पार्टीले एक–एक सिट जितेका थिए। अहिले हर्क साम्पाङ नेतृत्वको श्रम संस्कृति पार्टी प्रत्यक्षमा ३ र समानुपातिमा ४ गरी ७ सिटका साथ संसदमा प्रवेश गरेको छ।\n२०७९ मा प्रत्यक्षतर्फ ७ र समानुपातिकतर्फ ७ गरी १४ सिट जितेको राप्रपा अहिले प्रत्यक्षमा १ र समानुपातिकमा ४ गरी ५ सिटमा खुम्चिएको छ। २०७९ को निर्वाचनमा मोरङ ५ बाट योगेन्द्र मण्डल, सर्लाही ४ बाट अमरेशकुमार सिंह, रौतहट २ बाट किरणकुमार साह, रौतहट ३ बाट प्रभु साह र बर्दिया २ बाट लालवीर चौधरी स्वतन्त्र सांसदका रुपमा निर्वाचित भएका थिए। यसपटक रास्वपाको समर्थन पाएका महावीर पुन बाहेक कुनै पनि स्वतन्त्र उम्मेदवारले चुनाव जित्न सकेनन्। गत निर्वाचनपछि खुलेको प्रभु साह नेतृत्वको आम जनता पार्टी जितविहीन भयो।\n१२५ क्षेत्रमा जितेको रास्वपा अन्य पार्टीले जितेका ४० स्थान मध्ये ६ स्थानमा दोस्रो भएको छ। रास्वपाले चुनाव जितेका १२५ सिटमा कांग्रेस ७३, एमाले २७, नेकपा १०, जसपा ६, श्रम संस्कृति पार्टी २ तथा राप्रपा, उज्यालो नेपाल पार्टी, नेपाल मजदुर किसान पार्टी, नेपाल समाजवादी पार्टी, नागरिक उन्मुक्ति पार्टी र राष्ट्रिय स्वाभिमान पार्टी तथा स्वतन्त्र एक—एक ठाउँमा दोस्रो भएको देखिन्छ।\nरास्वपाको लहरका बाबजुद उसको उम्मेदवारका १३ निर्वाचन क्षेत्रमा जमानत जफत भएको छ। मनाङ र म्यादीमा भने उसले उम्मेदवारी दिएको थिएन। रुकुम पूर्व, जुम्ला, अछाम–१, डोल्पा, मुगु, जुम्ला, कालिकोट, हुम्ला, जाजरकोट, रुकमपश्चिम, पाँचथर, सोलुखुम्बु र खोटाङमा रास्वपाको जमानत जफत भएको छ।\nप्रतिक्रिया",
    "images": [
      "https://certify.alexametrics.com/atrk.gif?account=xp3Mn1QolK10uG",
      "https://nepalkhabar.prixacdn.net/media/albums/logo-np-inverse_KvRlHqXMS9.png",
      "https://nepalkhabar.prixacdn.net/static/normal/images/assets/unicode1.svg",
      "https://nepalkhabar.prixacdn.net/media/albums/logo-np-inverse_KvRlHqXMS9.png",
      "https://nepalkhabar.prixacdn.net/media/albums/logo-np-inverse_KvRlHqXMS9.png",
      "https://nepalkhabar.prixacdn.net/static/normal/images/assets/unicode1.svg",
      "https://nepalkhabar.prixacdn.net/static/normal/images/assets/unicode1.svg",
      "https://nepalkhabar.prixacdn.net/media/advertisements/825X100px_10_jhrMoWTdUQ.jpg",
      "https://nepalkhabar.prixacdn.net/media/advertisements/800X200px_9_GfHu0GxeAZ.jpg",
      "https://nepalkhabar.prixacdn.net/media/albums/gagan-rabi-kp-prachanda-sudurpashchim_A2csq0xO4c.jpg"
    ]
  },
  {
    "url": "https://www.ukeraa.com/news/detail/172281/",
    "title": "शुक्रबारदेखि आधा सिलिण्डर ग्यास मात्र पाइने, यस्तो छ कारण",
    "pub_date": "2026-03-12 21:56:57",
    "fetched_at": "2026-03-12T16:33:42.605873+00:00",
    "portal": "Ukeraa",
    "profiles_matched": [],
    "keywords_matched": [],
    "snippet": "शुक्रबारदेखि आधा सिलिण्डर ग्यास मात्र पाइने, यस्तो छ कारण\nकाठमाडौं : नेपाल आयल निगमले एलपी ग्यासको आपूर्ति र वितरणलाई सहज बनाउन आधा ग्यास (७.१ किलो) भरिएको सिलिण्डर मात्र बिक्री गर्ने निर्णय गरेको छ।\nनिगमले शुक्रबारदेखि लागू हुने गरी ७.१ किलो ग्यास भरिएको सिलिण्डर ९५५ रुपैयाँमा बिक्री वितरण गर्ने व्यवस्था मिलाएको हो।\nबिहीबार एक सूचना जारी गरेर निगमले सबै उपभोक्तालाई ग्यास उपलब्ध गराउने उद्देश्यले अर्को निर्णय नभएसम्मका लागि यो व्यवस्था लागू गरिएको जनाएको छ। निगमले आम उपभोक्तालाई सोही मूल्य र तौल",
    "content": "शुक्रबारदेखि आधा सिलिण्डर ग्यास मात्र पाइने, यस्तो छ कारण\nकाठमाडौं : नेपाल आयल निगमले एलपी ग्यासको आपूर्ति र वितरणलाई सहज बनाउन आधा ग्यास (७.१ किलो) भरिएको सिलिण्डर मात्र बिक्री गर्ने निर्णय गरेको छ।\nनिगमले शुक्रबारदेखि लागू हुने गरी ७.१ किलो ग्यास भरिएको सिलिण्डर ९५५ रुपैयाँमा बिक्री वितरण गर्ने व्यवस्था मिलाएको हो।\nबिहीबार एक सूचना जारी गरेर निगमले सबै उपभोक्तालाई ग्यास उपलब्ध गराउने उद्देश्यले अर्को निर्णय नभएसम्मका लागि यो व्यवस्था लागू गरिएको जनाएको छ। निगमले आम उपभोक्तालाई सोही मूल्य र तौलअनुसार मात्र ग्यास खरिद गर्न अनुरोधसमेत गरेको छ।\nनियमित रूपमा माग अनुरूप नै ग्यास आयात तथा वितरण भइरहे पनि पछिल्लो दुई-तीन महिनायता काठमाडौं उपत्यकामा ग्यासको माग उच्च देखिएको निगमले जनाएको छ।\nसाथै, मध्यपूर्वमा भइरहेको युद्धका कारण पेट्रोलियम पदार्थ तथा एलपी ग्यासको आपूर्तिमा विश्वव्यापी रूपमै असर परिरहेको र त्यसकै प्रभावका कारण हालको परिस्थितिलाई व्यवस्थित गर्न नयाँ निर्णय लिनुपरेको निगमले स्पष्ट पारेको छ।\nफागुन २८, २०८२ बिहीबार २१:५६:५७ मा प्रकाशित\nउकेरामा प्रकाशित सामाग्रीबारे प्रतिक्रिया, सल्लाह, सुझाव र कुनै सामाग्री भए [email protected] मा पठाउनु होला।",
    "images": [
      "https://ukeraa.prixacdn.net/media/albums/ukeraa_logo_zLaWQk8TUy.png",
      "https://ukeraa.prixacdn.net/media/albums/ukeraa_logo_zLaWQk8TUy.png",
      "https://ukeraa.prixacdn.net/media/albums/118157984_111588977332079_6228089157863869067_n-removebg-preview_3_e1opRCcu3T.png",
      "https://ukeraa.prixacdn.net/media/albums/Gas_ytwMskgSdY.jpg ",
      "https://ukeraa.prixacdn.net/media/albums/thumb_auout_karki_aayog_Iq8BlO0HN1.jpg",
      "https://ukeraa.prixacdn.net/media/albums/election-2082_final_h5tSHo4CR0.png",
      "https://ukeraa.prixacdn.net/media/albums/Jhalanath_Khanal_HzwppSLRyh.png",
      "https://ukeraa.prixacdn.net/media/albums/new_sansad_bhawan_HHuFWZw1rO.jpg",
      "https://ukeraa.prixacdn.net/media/albums/Rastriya_Dal_e2MddP0mxM.jpg",
      "https://ukeraa.prixacdn.net/media/albums/Rastriya_Dal_e2MddP0mxM.jpg"
    ]
  },
  {
    "url": "https://www.osnepal.com/detail/582818",
    "title": "नाडाको नवनिर्वाचित अध्यक्षलाई पदभार हस्तान्तरण तथा सपथ ग्रहण सम्पन्न",
    "pub_date": "2026-03-12 21:23:38",
    "fetched_at": "2026-03-12T16:33:46.234021+00:00",
    "portal": "Osnepal",
    "profiles_matched": [
      "Election Monitoring"
    ],
    "keywords_matched": [
      "निर्वाचन"
    ],
    "snippet": "काठमाडौं । नाडा अटोमोवाइल्स एशोसिएशन अफ नेपाल (नाडा) को केन्द्रीय कार्यसमितिको पहिलो बैठकमा नाडाका निवर्तमान अध्यक्ष करण चौधरीले नवनिर्वाचित अध्यक्ष सुरेन्द्रकुमार उप्रेतीलाई आफ्नो पदभार विधिवत रूपमा हस्तान्तरण गरेका छन् ।\nसो अवसरमा निवर्तमान अध्यक्ष चौधरीले नवनिर्वाचित अध्यक्ष उप्रेतीलाई सफल कार्यकालको शुभकामना व्यक्त गर्दै नाडाको संस्थागत विकास तथा अटोमोबाइल क्षेत्रको उन्नयनमा उहाँको नेतृत्व महत्वपूर्ण हुने विश्वास व्यक्त गरे ।\nयसै अवसरमा नवनिर्वाचित अध्यक्ष सुरेन्द्रकुमार उप्रेतीले पद तथा गोप",
    "content": "काठमाडौं । नाडा अटोमोवाइल्स एशोसिएशन अफ नेपाल (नाडा) को केन्द्रीय कार्यसमितिको पहिलो बैठकमा नाडाका निवर्तमान अध्यक्ष करण चौधरीले नवनिर्वाचित अध्यक्ष सुरेन्द्रकुमार उप्रेतीलाई आफ्नो पदभार विधिवत रूपमा हस्तान्तरण गरेका छन् ।\nसो अवसरमा निवर्तमान अध्यक्ष चौधरीले नवनिर्वाचित अध्यक्ष उप्रेतीलाई सफल कार्यकालको शुभकामना व्यक्त गर्दै नाडाको संस्थागत विकास तथा अटोमोबाइल क्षेत्रको उन्नयनमा उहाँको नेतृत्व महत्वपूर्ण हुने विश्वास व्यक्त गरे ।\nयसै अवसरमा नवनिर्वाचित अध्यक्ष सुरेन्द्रकुमार उप्रेतीले पद तथा गोपनीयताको सपथ ग्रहण गर्दै आफ्नो कार्यकालमा नाडाको उद्देश्य, विधान तथा मूल्य मान्यताहरू अनुरूप संस्थालाई अझ सशक्त, सक्रिय तथा प्रभावकारी बनाउने प्रतिबद्धता व्यक्त गरे ।\nउनले सम्पूर्ण सदस्य व्यवसायीहरूको हित संरक्षण, अटोमोबाइल क्षेत्रको विकास तथा सम्बन्धित सरोकारवाला निकायहरूसँग सहकार्य गर्दै अघि बढ्ने धारणा व्यक्त गरे ।उक्त बैठककै क्रममा नाडाका नवनिर्वाचित अध्यक्ष सुरेन्द्रकुमार उप्रेतीले नाडा विधान २०७८ को दफा २०.१ को ‘ङ’ बमोजिम श्री महेश पाल, श्री दीपककुमार अग्रवाल तथा राजेश गिरीलाई नाडाको केन्द्रीय कार्यसमितिको सदस्य पदमा मनोनयन गरेका छन् । उनले मनोनित सदस्यहरूलाई स्वागत गर्दै संस्थाको आगामी गतिविधिहरूमा सक्रिय भूमिका निर्वाह गर्ने अपेक्षा व्यक्त गरेका छन् ।\nसाथै, नाडाको केन्द्रीय कार्यसमितिले निकट भविष्यमै पदाधिकारीहरूको चयनका लागि निर्वाचन प्रक्रिया सम्पन्न गर्ने निर्णय समेत गरेको छ। आगामी दिनहरूमा नाडाले अटोमोबाइल क्षेत्रको समग्र विकास, व्यवसायीहरूको हकहित संरक्षण तथा नीतिगत सहकार्यलाई थप सुदृढ गर्दै अघि बढ्ने विश्वास व्यक्त गरेका छन् ।\nप्रकाशित मिति:\nबिहीबार, फागुन २८, २०८२",
    "images": [
      "https://www.osnepal.com/themes/osnepal/images/logo.png",
      "https://www.osnepal.com/themes/osnepal/images/android.png",
      "https://www.osnepal.com/themes/osnepal/images/ios.png",
      "https://www.osnepal.com/themes/osnepal/images/logo.png",
      "https://www.osnepal.com/uploads/authors/48141800.jpeg",
      "https://www.osnepal.com/uploads/posts/da-1773329901.jpg",
      "https://www.osnepal.com/uploads/posts/da-1773329901.jpg",
      "https://www.osnepal.com/uploads/posts/rain-1761878989.jpg",
      "https://www.osnepal.com/uploads/posts/myadi-1773328131.png",
      "https://www.osnepal.com/uploads/posts/gas-1773133043.jpg"
    ]
  },
  {
    "url": "https://www.osnepal.com/detail/582817",
    "title": "चितवन, गोरखा र उदयपुरमा भारी वर्षा,सबैभन्दा बढी उदयपुरमा",
    "pub_date": "2026-03-12 21:22:00",
    "fetched_at": "2026-03-12T16:33:50.382632+00:00",
    "portal": "Osnepal",
    "profiles_matched": [],
    "keywords_matched": [],
    "snippet": "काठमाडौँ । मौसम बदली भएसँगै बिहीबार दिउँसो चितवन, गोरखा र उदयपुरमा भारी वर्षा भएको छ । जल तथा मौसम विज्ञान विभागको अभिलेखअनुसार पछिल्लो ३ घण्टामा सबैभन्दा बढी उदयपुरमा ८२.२ मिलिमिटर वर्षा भएको छ।\nयस्तै गोरखामा ८० मिलिमिटर वर्षा भएको छ । विभागका अनुसार चितवनमा ६० मिलिमिटरभन्दा बढी वर्षा भएको छ । मापनका हिसाबले तीनवटै ठाउँमा भारी वर्षा हो । उदयपुरको कटारी र गोरखाको बारपाकमा बढी वर्षा भएको छ । चौबीस घण्टामा ५० मिलिमिटर माथिको वर्षालाई भारी वर्षामा गणना गरिन्छ।\nअन्य क्षेत्रमा पनि पानी परिरहेको विभाग",
    "content": "काठमाडौँ । मौसम बदली भएसँगै बिहीबार दिउँसो चितवन, गोरखा र उदयपुरमा भारी वर्षा भएको छ । जल तथा मौसम विज्ञान विभागको अभिलेखअनुसार पछिल्लो ३ घण्टामा सबैभन्दा बढी उदयपुरमा ८२.२ मिलिमिटर वर्षा भएको छ।\nयस्तै गोरखामा ८० मिलिमिटर वर्षा भएको छ । विभागका अनुसार चितवनमा ६० मिलिमिटरभन्दा बढी वर्षा भएको छ । मापनका हिसाबले तीनवटै ठाउँमा भारी वर्षा हो । उदयपुरको कटारी र गोरखाको बारपाकमा बढी वर्षा भएको छ । चौबीस घण्टामा ५० मिलिमिटर माथिको वर्षालाई भारी वर्षामा गणना गरिन्छ।\nअन्य क्षेत्रमा पनि पानी परिरहेको विभागले जनाएको छ। विभागका अनुसार लमजुङ, मकवानपुर, सिन्धुपाल्चोक, सङ्खुवासभा, इलाम, सोलुखुम्बु, मुस्ताङ, बर्दिया, कास्कीलगायत जिल्लामा पनि वर्षा भएको छ।यो वर्षापछि प्रदूषण केही कम हुने अनुमान गरिएको विभागका सूचना अधिकारी दिनकर कायस्थले जानकारी दिए।\nप्रकाशित मिति:\nबिहीबार, फागुन २८, २०८२",
    "images": [
      "https://www.osnepal.com/themes/osnepal/images/logo.png",
      "https://www.osnepal.com/themes/osnepal/images/android.png",
      "https://www.osnepal.com/themes/osnepal/images/ios.png",
      "https://www.osnepal.com/themes/osnepal/images/logo.png",
      "https://www.osnepal.com/uploads/authors/48141800.jpeg",
      "https://www.osnepal.com/uploads/posts/rain-1761878989.jpg",
      "https://www.osnepal.com/uploads/posts/da-1773329901.jpg",
      "https://www.osnepal.com/uploads/posts/rain-1761878989.jpg",
      "https://www.osnepal.com/uploads/posts/myadi-1773328131.png",
      "https://www.osnepal.com/uploads/posts/gas-1773133043.jpg"
    ]
  }
]